MODEL/apb_exe_unit_3/exe_unit_3/include.sv
`ifndef ALU_DEF

`define ALU_DEF
`include "./MODEL/apb_exe_unit_3/exe_unit_3/bit_set/bit_set.sv"
`include "./MODEL/apb_exe_unit_3/exe_unit_3/bit_shift/bit_shift.sv"
`include "./MODEL/apb_exe_unit_3/exe_unit_3/comparator/comparator.sv"
`include "./MODEL/apb_exe_unit_3/exe_unit_3/u2_to_sm/u2_to_sm.sv"
`include "./MODEL/apb_exe_unit_3/exe_unit_3/MUX.sv"
`include "./MODEL/apb_exe_unit_3/exe_unit_3/reg.sv"
  
`endif

MODEL/apb_exe_unit_3/exe_unit_3/reg.sv
module regg #(parameter M=8)
(input logic i_clk,
 input logic i_reset,
 input logic [M-1:0] i_in,
 output logic [M-1:0] o_out);

always_ff @(posedge i_clk)
begin
    if(i_reset == 1'b1)
    o_out <= i_in;
    else 
    o_out <= '0;
    
end
endmodule

MODEL/apb_exe_unit_3/exe_unit_3/MUX.sv
module MUX #(parameter M = 8, parameter N = 2)
(input logic [M-1:0] SET,
input logic [M-1:0] SHIFT,
input logic [M-1:0] COMPARATOR,
input logic [M-1:0] CHANGER,
input [N-1:0] testcase,
output logic [M-1:0] modul);

always_comb
begin
    case(testcase)
    2'b00: modul = SET;
    2'b01: modul = SHIFT;
    2'b10: modul = COMPARATOR;
    2'b11: modul = CHANGER;
    endcase
end

endmodule

MODEL/apb_exe_unit_3/exe_unit_3/u2_to_sm/u2_to_sm.sv
module u2_to_sm #(parameter M=8)(u2, sm, ERROR);

input logic[M-1:0] u2; //M-bitowe wejscie
output logic[M-1:0] sm; //M-bitowe wyjscie (po zamianie z U2 na ZNAK-MODUL)
output logic ERROR; //blad

//changing function
always@(*) begin
    if(u2[M-1] == 1)
    begin
        sm = {1'b1, {~u2[M-2:0]}} + 1;
        ERROR = sm[M-1] == 0; //szukanie bledu typu OVERFLOW
    end
    else 
    begin
        sm = u2;
        ERROR = 0; //zerowanie bledu
    end
end

endmodule

MODEL/apb_exe_unit_3/exe_unit_3/comparator/comparator.sv
module comparator #(parameter M=8)(i_argA, i_argB, o_y);

input logic [M-1:0] i_argA; //M-bitowe wejscie A
input logic [M-1:0] i_argB; //M-bitowe wejscie B
output logic [M-1:0] o_y; //wyjscie

always @(i_argA or i_argB)
	begin
		if(i_argA > i_argB)	
			begin
				o_y = 0;
			end
		else
			begin
				o_y = 1;
			end
			
	end

endmodule

MODEL/apb_exe_unit_3/exe_unit_3/bit_shift/bit_shift.sv
module bit_shift #(parameter M=8)( i_argA, i_argB, o_y, ERROR);

	//input
	input logic [M-1:0] i_argA; //M-bitowe wejscie A
	input logic [M-1:0] i_argB; //M-bitowe wejscie B
	//output
	output logic [M-1:0] o_y; //wyjscie
	output logic ERROR; //blad
	
	always@(*) begin
		ERROR = 0; //'zerowanie' bledu na starcie
		if(i_argB < 'b0)
		begin
			ERROR = 1; //pojawienie sie bledu
			o_y = 0; //wyjscie wynosi 0
		end
		else 
		begin
			ERROR = 0; //blad sie 'zeruje'
			o_y = i_argA <<< i_argB; //left shifting
		end
	end

endmodule

MODEL/apb_exe_unit_3/exe_unit_3/bit_set/bit_set.sv
module bit_set #(parameter M=8)(i_argA, i_argB, ERROR, o_y);
    
    //inputs & outputs
    input logic [M-1:0] i_argA; //M-bitowe wejscie A
    input logic [M-1:0] i_argB; //M-bitowe wejscie B
    output logic ERROR; // wyjscie bledu
    output logic [M-1:0] o_y; //wejscie zmienionego A

    //function
        always@(*) begin
            if(i_argB < 0 || i_argB >= M)
            begin
                ERROR = 1; //Blad jezeli B jest poza zakresem
                o_y = i_argA; //Wtedy A jest bez zmian
            end
            else
            begin
                ERROR = 0; //Blad sie 'zeruje'
                o_y= i_argA;
                o_y[i_argB] = 1;
            end
        end

endmodule

MODEL/apb_exe_unit_3/exe_unit_3/exe_unit_w38.sv
`include "./MODEL/apb_exe_unit_3/exe_unit_3/include.sv"
  
module exe_unit_w38 #(parameter M=8, parameter N=2)(i_op, i_argA, i_argB, i_clk, i_reset, o_result, o_stat);
	input logic [N-1:0] i_op; //wybiera operacje - MUX
	input logic [M-1:0] i_argA; //M-bitowe wejscie A
	input logic [M-1:0] i_argB; //M-bitowe wejscie B
	input logic i_reset; //reset
	input logic i_clk; //zegar
	output logic [M-1:0] o_result; //wyjscie
	output logic [3:0] o_stat; //wyjscie dla bledow


    //sygnaly wewnetrzne
    logic [M-1:0] s_out_set; //bit_set
    logic [M-1:0] s_out_shift; //bit_shift
    logic [M-1:0] s_out_comparator; //comparator
    logic [M-1:0] s_out_changer; //u2_to_sm

    logic [M-1:0] s_oper_mux; //wyjscie z muxa, operacje
    logic s_ERROR_set; //ERROR dla bit_set
    logic s_ERROR_shift; //ERROR dla bit_shift
    logic s_ERROR_change; //ERROR dla u2_to_sm
    logic [3:0] possible_errors; //wyjscie dla wszelakich znacznikow

    //Dolaczanie modulow:
    bit_set     #(.M(M))   setter    
    (.i_argA(i_argA),
     .i_argB(i_argB),
     .o_y(s_out_set),
     .ERROR(s_ERROR_set));

    bit_shift #(.M(M)) shifter 
    (.i_argA(i_argA),
     .i_argB(i_argB),
     .o_y(s_out_shift),
     .ERROR(s_ERROR_shift));

    comparator #(.M(M)) comparator 
    (.i_argA(i_argA),
    .i_argB(i_argB),
    .o_y(s_out_comparator));

    u2_to_sm #(.M(M)) changer 
    (.u2(i_argA),
     .sm(s_out_changer),
     .ERROR(s_ERROR_change)
     );

    MUX #(.M(M), .N(N)) MUX (.SET(s_out_set),
      .SHIFT(s_out_shift),
      .COMPARATOR(s_out_comparator),
      .CHANGER(s_out_changer),
      .testcase(i_op),
      .modul(s_oper_mux)
    );

    regg #(M) register (
        .i_clk(i_clk),
        .i_reset(i_reset),
        .i_in(s_oper_mux),
        .o_out(o_result)
    );

     regg #(4) register_error (
      .i_clk(i_clk),
      .i_reset(i_reset),
      .i_in(possible_errors),
      .o_out(o_stat)
     );

    integer counter, i; //helper w zliczaniu
	always_comb
begin
    counter = 0;
    for (i = 0; i < M; i = i + 1)
    begin 
        if (o_result[i] == 1) begin
            counter = counter + 1;
        end
    end 

    possible_errors[0] = (counter % 2 == 0); // EVEN
    possible_errors[1] = (&o_result); // ONES
    possible_errors[2] = s_ERROR_change; // OVERFLOW
    possible_errors[3] = s_ERROR_set || s_ERROR_shift; // ERROR
end

    
endmodule

MODEL/apb_exe_unit_3/apb_exe_unit_3.sv
`include "./MODEL/apb_exe_unit_3/exe_unit_3/exe_unit_w38.sv"

// iverilog -g2005-sv -o ./TEST/VVP/apb_exe_unit_3.vvp ./MODEL/apb_exe_unit_3/apb_exe_unit_3.sv

module apb_exe_unit_3 #(
    parameter SEL_WIDTH = 3,
    parameter ADDR_WIDTH = 2,
    parameter DATA_WIDTH = 32,
    parameter SEL_BIT = 3
)(
    input logic i_PCLK,                     
    input logic i_PWRITE,
    input logic i_PENABLE,                  
    input logic i_PRESETn,  
    input logic [ADDR_WIDTH-1:0] i_PADDR,   
    input logic [DATA_WIDTH-1:0] i_PWDATA,     
    input logic [SEL_WIDTH-1:0] i_PSEL,
       
    output logic o_PREADY,
    output logic [3:0] o_PSLVERR,
    output logic [DATA_WIDTH-1:0] o_PRDATA
);

    logic [3:0] s_pslverr;

    logic [DATA_WIDTH/2-1:0] s_result;
    logic [ADDR_WIDTH-1:0] s_PADDR;   
    logic [DATA_WIDTH-1:0] s_PWDATA;     


    exe_unit_w38 #(.N(ADDR_WIDTH), .M(DATA_WIDTH/2)) slave (.i_clk(i_PCLK), 
                                                            .i_op(s_PADDR),
                                                            .i_argA(s_PWDATA[DATA_WIDTH/2-1:0]), 
                                                            .i_argB(s_PWDATA[DATA_WIDTH-1:DATA_WIDTH/2]), 
                                                            .o_result(s_result), 
                                                            .o_stat(s_pslverr));

    always_ff @(posedge i_PCLK or negedge i_PRESETn) begin
        if (!i_PRESETn) begin // RESET
            o_PREADY <= 1'b0;
            o_PRDATA <= 'b0;
            o_PSLVERR <= 1'b0;
        end else if (i_PENABLE && i_PSEL[SEL_BIT-1] == 1 && i_PWRITE == 1) begin // ZAPIS (MASTER -> SLAVE)
            s_PADDR <= i_PADDR;
            s_PWDATA <= i_PWDATA;
            o_PREADY <= 1'b1;
            o_PSLVERR <= s_pslverr;
        end else if (i_PENABLE && i_PSEL[SEL_BIT-1] == 1 && i_PWRITE == 0) begin // ODCZYT (SLAVE -> MASTER)
            o_PREADY <= 1'b1;
            o_PRDATA <= {{(DATA_WIDTH/2){1'b0}},{s_result}};
            o_PSLVERR <= s_pslverr;
        end else begin
            o_PREADY <= 'b0;
            o_PRDATA <= 'b0;
            o_PSLVERR <= 'b0;
        end
    end
endmodule

TEST/tb_apb_exe_unit_3.sv
`include "./MODEL/apb_exe_unit_3/apb_exe_unit_3.sv"


// Komendy z poziomu sck-grupowy
// iverilog -g2005-sv -o ./TEST/VVP/tb_apb_exe_unit_3.vvp ./TEST/tb_apb_exe_unit_3.sv
// vvp ./TEST/VVP/tb_apb_exe_unit_3.vvp   

module testbench;

  parameter SEL_WIDTH = 3;
  parameter ADDR_WIDTH = 2;
  parameter DATA_WIDTH = 8;

  logic i_PCLK = 0;                 
  logic i_PWRITE;
  logic i_PENABLE;                  
  logic i_PRESETn;                  
  logic [ADDR_WIDTH-1:0] i_PADDR;   
  logic [DATA_WIDTH-1:0] i_PWDATA;
  logic [SEL_WIDTH-1:0] i_PSEL;    

  logic o_PREADY;
  logic [DATA_WIDTH-1:0] o_PRDATA;
  logic [3:0] o_PSLVERR;

  always #1 i_PCLK = ~i_PCLK;

  apb_exe_unit_3 #(.SEL_WIDTH(SEL_WIDTH), .ADDR_WIDTH(ADDR_WIDTH), .DATA_WIDTH(DATA_WIDTH), .SEL_BIT(3)) slave (
  .i_PCLK(i_PCLK), 
  .i_PWRITE(i_PWRITE), 
  .i_PENABLE(i_PENABLE), 
  .i_PRESETn(i_PRESETn),
  .i_PADDR(i_PADDR), 
  .i_PWDATA(i_PWDATA), 
  .i_PSEL(i_PSEL),

  .o_PREADY(o_PREADY),
  .o_PRDATA(o_PRDATA),
  .o_PSLVERR(o_PSLVERR)
  );

   initial begin

    $dumpfile("./TEST/VCD/tb_apb_exe_unit_3.vcd");
    $dumpvars(0, testbench);

    // Inicjalizacja

    i_PWRITE = 1;
    i_PRESETn = 0;
    i_PENABLE = 'b0;

    i_PADDR = 'b0;
    i_PWDATA = 'b0;
    i_PSEL = 'b0;

    #6;
    i_PRESETn = 0;
    i_PENABLE = 'b0;

    #6;
    i_PRESETn = 1;


    // Przesun 1010 o 1 bit w lewo z zachowaniem znaku
    #6;
    i_PWRITE = 1;
    i_PADDR = 'b01;
    i_PSEL = 3'b001;
    i_PWDATA = 'b00011010;

    #2;
    i_PENABLE = 'b1;

    #8;
    i_PENABLE = 'b0;
    i_PWDATA = 'b0;
    i_PSEL = 3'b000;
    i_PADDR = 'b00;

    // Odczyt
    #6;
    i_PWRITE = 0;
    i_PENABLE = 'b0;
    i_PWDATA = 'b0;
    i_PSEL = 3'b001;
    i_PADDR = 'b00;

    #2;
    i_PENABLE = 'b1;

    #8;
    i_PENABLE = 'b0;
    i_PWDATA = 'b0;
    i_PSEL = 3'b000;
    i_PADDR = 'b00;

    // Przekonwertuj 1010 na ZM
    #6;
    i_PWRITE = 1;
    i_PADDR = 'b00;
    i_PSEL = 3'b001;
    i_PWDATA = 'b00101010;

    #2;
    i_PENABLE = 'b1;

    #8;
    i_PENABLE = 'b0;
    i_PWDATA = 'b0;
    i_PSEL = 3'b000;
    i_PADDR = 'b00;

    // Odczyt
    #6;
    i_PWRITE = 0;
    i_PENABLE = 'b0;
    i_PWDATA = 'b0;
    i_PSEL = 3'b001;
    i_PADDR = 'b00;

    #2;
    i_PENABLE = 'b1;

    #8;
    i_PENABLE = 'b0;
    i_PWDATA = 'b0;
    i_PSEL = 3'b000;
    i_PADDR = 'b00;

    
    // Przesun 1010 o 1 bit w lewo z zachowaniem znaku
    #6;
    i_PWRITE = 1;
    i_PADDR = 'b11;
    i_PSEL = 3'b001;
    i_PWDATA = 'b00001010;

    #2;
    i_PENABLE = 'b1;

    #8;
    i_PENABLE = 'b0;
    i_PWDATA = 'b0;
    i_PSEL = 3'b000;
    i_PADDR = 'b00;

    // Odczyt
    #6;
    i_PWRITE = 0;
    i_PENABLE = 'b0;
    i_PWDATA = 'b0;
    i_PSEL = 3'b001;
    i_PADDR = 'b00;

    #2;
    i_PENABLE = 'b1;

    #8;
    i_PENABLE = 'b0;
    i_PWDATA = 'b0;
    i_PSEL = 3'b000;
    i_PADDR = 'b00;

    // Przesun 1010 o 1 bit w lewo z zachowaniem znaku
    #6;
    i_PWRITE = 1;
    i_PADDR = 'b10;
    i_PSEL = 3'b001;
    i_PWDATA = 'b00110010;

    #2;
    i_PENABLE = 'b1;

    #8;
    i_PENABLE = 'b0;
    i_PWDATA = 'b0;
    i_PSEL = 3'b000;
    i_PADDR = 'b00;

    // Odczyt
    #6;
    i_PWRITE = 0;
    i_PENABLE = 'b0;
    i_PWDATA = 'b0;
    i_PSEL = 3'b001;
    i_PADDR = 'b00;

    #2;
    i_PENABLE = 'b1;

    #8;
    i_PENABLE = 'b0;
    i_PWDATA = 'b0;
    i_PSEL = 3'b000;
    i_PADDR = 'b00;

  end

  initial #150 $finish;

endmodule

TEST/VCD/tb_apb_exe_unit_3.vcd
$date
	Tue Jan 23 15:31:17 2024
$end
$version
	Icarus Verilog
$end
$timescale
	1s
$end
$scope module testbench $end
$var wire 4 ! o_PSLVERR [3:0] $end
$var wire 1 " o_PREADY $end
$var wire 8 # o_PRDATA [7:0] $end
$var parameter 32 $ ADDR_WIDTH $end
$var parameter 32 % DATA_WIDTH $end
$var parameter 32 & SEL_WIDTH $end
$var reg 2 ' i_PADDR [1:0] $end
$var reg 1 ( i_PCLK $end
$var reg 1 ) i_PENABLE $end
$var reg 1 * i_PRESETn $end
$var reg 3 + i_PSEL [2:0] $end
$var reg 8 , i_PWDATA [7:0] $end
$var reg 1 - i_PWRITE $end
$scope module slave $end
$var wire 2 . i_PADDR [1:0] $end
$var wire 1 ( i_PCLK $end
$var wire 1 ) i_PENABLE $end
$var wire 1 * i_PRESETn $end
$var wire 3 / i_PSEL [2:0] $end
$var wire 8 0 i_PWDATA [7:0] $end
$var wire 1 - i_PWRITE $end
$var wire 4 1 s_result [3:0] $end
$var wire 4 2 s_pslverr [3:0] $end
$var parameter 32 3 ADDR_WIDTH $end
$var parameter 32 4 DATA_WIDTH $end
$var parameter 32 5 SEL_BIT $end
$var parameter 32 6 SEL_WIDTH $end
$var reg 8 7 o_PRDATA [7:0] $end
$var reg 1 " o_PREADY $end
$var reg 4 8 o_PSLVERR [3:0] $end
$var reg 2 9 s_PADDR [1:0] $end
$var reg 8 : s_PWDATA [7:0] $end
$scope module slave $end
$var wire 4 ; i_argA [3:0] $end
$var wire 4 < i_argB [3:0] $end
$var wire 1 ( i_clk $end
$var wire 2 = i_op [1:0] $end
$var wire 1 > i_reset $end
$var wire 4 ? s_out_shift [3:0] $end
$var wire 4 @ s_out_set [3:0] $end
$var wire 4 A s_out_comparator [3:0] $end
$var wire 4 B s_out_changer [3:0] $end
$var wire 4 C s_oper_mux [3:0] $end
$var wire 1 D s_ERROR_shift $end
$var wire 1 E s_ERROR_set $end
$var wire 1 F s_ERROR_change $end
$var wire 4 G o_stat [3:0] $end
$var wire 4 H o_result [3:0] $end
$var parameter 32 I M $end
$var parameter 32 J N $end
$var reg 4 K possible_errors [3:0] $end
$var integer 32 L counter [31:0] $end
$var integer 32 M i [31:0] $end
$scope module MUX $end
$var wire 2 N testcase [1:0] $end
$var wire 4 O SHIFT [3:0] $end
$var wire 4 P SET [3:0] $end
$var wire 4 Q COMPARATOR [3:0] $end
$var wire 4 R CHANGER [3:0] $end
$var parameter 32 S M $end
$var parameter 32 T N $end
$var reg 4 U modul [3:0] $end
$upscope $end
$scope module changer $end
$var wire 4 V u2 [3:0] $end
$var parameter 32 W M $end
$var reg 1 F ERROR $end
$var reg 4 X sm [3:0] $end
$upscope $end
$scope module comparator $end
$var wire 4 Y i_argA [3:0] $end
$var wire 4 Z i_argB [3:0] $end
$var parameter 32 [ M $end
$var reg 4 \ o_y [3:0] $end
$upscope $end
$scope module register $end
$var wire 1 ( i_clk $end
$var wire 4 ] i_in [3:0] $end
$var wire 1 > i_reset $end
$var parameter 32 ^ M $end
$var reg 4 _ o_out [3:0] $end
$upscope $end
$scope module register_error $end
$var wire 1 ( i_clk $end
$var wire 4 ` i_in [3:0] $end
$var wire 1 > i_reset $end
$var parameter 32 a M $end
$var reg 4 b o_out [3:0] $end
$upscope $end
$scope module setter $end
$var wire 4 c i_argA [3:0] $end
$var wire 4 d i_argB [3:0] $end
$var parameter 32 e M $end
$var reg 1 E ERROR $end
$var reg 4 f o_y [3:0] $end
$upscope $end
$scope module shifter $end
$var wire 4 g i_argA [3:0] $end
$var wire 4 h i_argB [3:0] $end
$var parameter 32 i M $end
$var reg 1 D ERROR $end
$var reg 4 j o_y [3:0] $end
$upscope $end
$upscope $end
$upscope $end
$upscope $end
$enddefinitions $end
$comment Show the parameter values. $end
$dumpall
b100 i
b100 e
b100 a
b100 ^
b100 [
b100 W
b10 T
b100 S
b10 J
b100 I
b11 6
b11 5
b1000 4
b10 3
b11 &
b1000 %
b10 $
$end
#0
$dumpvars
bx j
bx h
bx g
bx f
bx d
bx c
bx b
bx1 `
bx _
bx ]
bx \
bx Z
bx Y
bx X
bx V
bx U
bx R
bx Q
bx P
bx O
bx N
b100 M
b0 L
bx1 K
bx H
bx G
xF
xE
xD
bx C
bx B
bx A
bx @
bx ?
z>
bx =
bx <
bx ;
bx :
bx 9
b0 8
b0 7
bx 2
bx 1
b0 0
b0 /
b0 .
1-
b0 ,
b0 +
0*
0)
0(
b0 '
b0 #
0"
b0 !
$end
#1
bx01 K
bx01 `
b100 M
b0 1
b0 H
b0 _
b0 2
b0 G
b0 b
1(
#2
0(
#3
1(
#4
0(
#5
1(
#6
0(
#7
1(
#8
0(
#9
1(
#10
0(
#11
1(
#12
0(
1*
#13
1(
#14
0(
#15
1(
#16
0(
#17
1(
#18
0(
b11010 ,
b11010 0
b1 +
b1 /
b1 '
b1 .
#19
1(
#20
0(
1)
#21
1(
#22
0(
#23
1(
#24
0(
#25
1(
#26
0(
#27
1(
#28
0(
b0 '
b0 .
b0 +
b0 /
b0 ,
b0 0
0)
#29
1(
#30
0(
#31
1(
#32
0(
#33
1(
#34
0(
b1 +
b1 /
0-
#35
1(
#36
0(
1)
#37
1(
#38
0(
#39
1(
#40
0(
#41
1(
#42
0(
#43
1(
#44
0(
b0 +
b0 /
0)
#45
1(
#46
0(
#47
1(
#48
0(
#49
1(
#50
0(
b101010 ,
b101010 0
b1 +
b1 /
1-
#51
1(
#52
0(
1)
#53
1(
#54
0(
#55
1(
#56
0(
#57
1(
#58
0(
#59
1(
#60
0(
b0 +
b0 /
b0 ,
b0 0
0)
#61
1(
#62
0(
#63
1(
#64
0(
#65
1(
#66
0(
b1 +
b1 /
0-
#67
1(
#68
0(
1)
#69
1(
#70
0(
#71
1(
#72
0(
#73
1(
#74
0(
#75
1(
#76
0(
b0 +
b0 /
0)
#77
1(
#78
0(
#79
1(
#80
0(
#81
1(
#82
0(
b1010 ,
b1010 0
b1 +
b1 /
b11 '
b11 .
1-
#83
1(
#84
0(
1)
#85
1(
#86
0(
#87
1(
#88
0(
#89
1(
#90
0(
#91
1(
#92
0(
b0 '
b0 .
b0 +
b0 /
b0 ,
b0 0
0)
#93
1(
#94
0(
#95
1(
#96
0(
#97
1(
#98
0(
b1 +
b1 /
0-
#99
1(
#100
0(
1)
#101
1(
#102
0(
#103
1(
#104
0(
#105
1(
#106
0(
#107
1(
#108
0(
b0 +
b0 /
0)
#109
1(
#110
0(
#111
1(
#112
0(
#113
1(
#114
0(
b110010 ,
b110010 0
b1 +
b1 /
b10 '
b10 .
1-
#115
1(
#116
0(
1)
#117
1(
#118
0(
#119
1(
#120
0(
#121
1(
#122
0(
#123
1(
#124
0(
b0 '
b0 .
b0 +
b0 /
b0 ,
b0 0
0)
#125
1(
#126
0(
#127
1(
#128
0(
#129
1(
#130
0(
b1 +
b1 /
0-
#131
1(
#132
0(
1)
#133
1(
#134
0(
#135
1(
#136
0(
#137
1(
#138
0(
#139
1(
#140
0(
b0 +
b0 /
0)
