MODEL/apb_exe_unit_2/exe_unit_2/Modules/changecode.sv
module changecode (i_argA, o_result, error);
    parameter BITS = 4;

    input logic signed [BITS-1:0] i_argA;   
    output logic signed [BITS-1:0] o_result;
    output logic error;

always_comb
  begin
    if (i_argA >= 0)
    begin
      error = 0;
      o_result = i_argA;
    end
    else if (i_argA == -(2**(BITS-1)))
    begin
      error = 1;
      o_result = i_argA;
    end
    else 
    begin
      error = 0;
      o_result = ~i_argA + 1 | (1 << (BITS-1));
    end
  end
endmodule

MODEL/apb_exe_unit_2/exe_unit_2/Modules/changebit.sv
module changebit (i_argA, i_argB, o_result, error);
    parameter BITS = 4;

    input logic [BITS-1:0] i_argA;   
    input logic signed [BITS-1:0] i_argB;
    output logic [BITS-1:0] o_result;
    output logic error;

always_comb
  begin
    if (i_argB < 0 || i_argB >= BITS)
    begin
      error = 1;
      o_result = i_argA;
    end
    else
    begin
      error = 0;
      o_result = i_argA | (1 << i_argB);
    end
  end
endmodule

MODEL/apb_exe_unit_2/exe_unit_2/Modules/comparison.sv
module comparison (i_argA, i_argB, o_result);
    parameter BITS = 4;

    input logic signed [BITS-1:0] i_argA;
    input logic signed [BITS-1:0] i_argB;
    output logic [BITS-1:0] o_result;

    always_comb begin
        if (i_argA > i_argB) 
        begin
            o_result = 'b1;
        end 
        else if (i_argA==i_argB)
        begin
            o_result = 'b1;
        end
        else 
        begin
            o_result = 'b0;
        end
    end
endmodule

MODEL/apb_exe_unit_2/exe_unit_2/Modules/negation.sv
module negation (i_argA, o_result, error);
    parameter BITS = 4;

    input logic signed [BITS-1:0] i_argA;
    output logic signed [BITS-1:0] o_result;
    output logic error;

    always_comb
    begin
        if (i_argA == -(2**(BITS-1)))
        begin
            error = 1;
            o_result = i_argA;
        end
        else
        begin
            error = 0;
            o_result = ~i_argA + 1;
        end
    end
endmodule

MODEL/apb_exe_unit_2/exe_unit_2/Modules/exe_unit_w22.sv
`include "./MODEL/apb_exe_unit_2/exe_unit_2/Modules/negation.sv"
`include "./MODEL/apb_exe_unit_2/exe_unit_2/Modules/comparison.sv"
`include "./MODEL/apb_exe_unit_2/exe_unit_2/Modules/changebit.sv"
`include "./MODEL/apb_exe_unit_2/exe_unit_2/Modules/changecode.sv"

module exe_unit_w22 (i_argA, i_argB, i_oper, i_clk, i_rsn, o_result, o_status);
    parameter BITS = 4;
    parameter N = 2;

    input logic [BITS-1:0] i_argA;
    input logic [BITS-1:0] i_argB;
    input logic [N-1:0] i_oper;

    input logic i_clk;
    input logic i_rsn;

    output logic [BITS-1:0] o_result;
    output logic [3:0] o_status;

    logic error;
    logic overflow;

    logic [BITS-1:0] o_result_0;
    logic [BITS-1:0] o_result_1;
    logic [BITS-1:0] o_result_2;
    logic [BITS-1:0] o_result_3;
    logic error_0;
    logic error_2;
    logic error_3;

    integer i;
    integer x;

    negation #(BITS) negation (
        .i_argA(i_argA),
        .o_result(o_result_0),
        .error(error_0)
    );

    comparison #(BITS) comparison (
        .i_argA(i_argA),
        .i_argB(i_argB),
        .o_result(o_result_1)
    );

    changebit #(BITS) changebit (
        .i_argA(i_argA),
        .i_argB(i_argB),
        .o_result(o_result_2),
        .error(error_2)
    );

    changecode #(BITS) changecode (
        .i_argA(i_argA),
        .o_result(o_result_3),
        .error(error_3)
    );

    always_ff @(posedge i_clk, negedge i_rsn)
    begin
        if (i_rsn == 0)
        begin
            o_result = 0;
            o_status = 0;
        end
        else
        begin
        case (i_oper)
            0:
            begin
                error = error_0;
                overflow = error_0;
                o_result = o_result_0;
            end
            1:
            begin
                error = 0;
                overflow = 0;
                o_result = o_result_1;
            end
            2:
            begin
                error = error_2;
                overflow = 0;
                o_result = o_result_2;
            end
            3:
            begin
                error = error_3;
                overflow = error_3;
                o_result = o_result_3;
            end
            default:
            begin
                o_result = 0;
            end   
        endcase
//ERROR
        if (error == 1)
        begin
            o_status[3] = 1;
        end
        else
        begin
            o_status[3] = 0;
        end
//OVERFLOW
        if (overflow == 1)
        begin 
            o_status[2] = 1;
        end
        else
        begin
            o_status[2] = 0;
        end
//ODD
        x = 0;
        for (i=0; i<BITS; i++)
        begin
        if (o_result[i] == 1) 
            x=x+1;
        end
        if (x%2 != 0) 
        begin
            o_status[1] = 1;
        end
        else
        begin
            o_status[1] = 0;
        end
//ZERO
        if (o_result == '0)
        begin
            o_status[0] = 1;
        end
        else
        begin
            o_status[0] = 0;          
        end  
    end
    end
endmodule

MODEL/apb_exe_unit_2/apb_exe_unit_2.sv
`include "./MODEL/apb_exe_unit_2/exe_unit_2/Modules/exe_unit_w22.sv"

// iverilog -g2005-sv -o ./TEST/VVP/apb_exe_unit_2.vvp ./MODEL/apb_exe_unit_2/apb_exe_unit_2.sv

module apb_exe_unit_2 #(
    parameter SEL_WIDTH = 3,
    parameter ADDR_WIDTH = 2,
    parameter DATA_WIDTH = 32,
    parameter SEL_BIT = 2
)(
    input logic i_PCLK,                     
    input logic i_PWRITE,
    input logic i_PENABLE,                  
    input logic i_PRESETn,  
    input logic [ADDR_WIDTH-1:0] i_PADDR,   
    input logic [DATA_WIDTH-1:0] i_PWDATA,     
    input logic [SEL_WIDTH-1:0] i_PSEL,
       
    output logic o_PREADY,
    output logic [3:0] o_PSLVERR,
    output logic [DATA_WIDTH-1:0] o_PRDATA
);

    logic [3:0] s_pslverr;
    logic [DATA_WIDTH/2-1:0] s_result;
    logic [ADDR_WIDTH-1:0] s_PADDR;   
    logic [DATA_WIDTH-1:0] s_PWDATA;     


    exe_unit_w22 #(.N(ADDR_WIDTH), .BITS(DATA_WIDTH/2)) slave (
        .i_clk(i_PCLK), 
        .i_oper(s_PADDR), 
        .i_argA(s_PWDATA[DATA_WIDTH/2-1:0]), 
        .i_argB(s_PWDATA[DATA_WIDTH-1:DATA_WIDTH/2]), 
        .o_result(s_result), 
        .o_status(s_pslverr)
    );

    always_ff @(posedge i_PCLK or negedge i_PRESETn) begin
        if (!i_PRESETn) begin // RESET
            o_PREADY <= 1'b0;
            o_PRDATA <= 'b0;
            o_PSLVERR <= 1'b0;
        end else if (i_PENABLE && i_PSEL[SEL_BIT-1] == 1 && i_PWRITE == 1) begin // ZAPIS (MASTER -> SLAVE)
            s_PADDR <= i_PADDR;
            s_PWDATA <= i_PWDATA;
            o_PREADY <= 1'b1;
            o_PSLVERR <= s_pslverr;
        end else if (i_PENABLE && i_PSEL[SEL_BIT-1] == 1 && i_PWRITE == 0) begin // ODCZYT (SLAVE -> MASTER)
            o_PREADY <= 1'b1;
            o_PRDATA <= {{(DATA_WIDTH/2){1'b0}},{s_result}};
            o_PSLVERR <= s_pslverr;
        end else begin
            o_PREADY <= 'b0;
            o_PRDATA <= 'b0;
            o_PSLVERR <= 'b0;
        end
    end
endmodule

TEST/tb_apb_exe_unit_2.sv
`include "./MODEL/apb_exe_unit_2/apb_exe_unit_2.sv"


// Komendy z poziomu sck-grupowy
// iverilog -g2005-sv -o ./TEST/VVP/tb_apb_exe_unit_2.vvp ./TEST/tb_apb_exe_unit_2.sv
// vvp ./TEST/VVP/tb_apb_exe_unit_2.vvp   

module testbench;

  parameter SEL_WIDTH = 3;
  parameter ADDR_WIDTH = 2;
  parameter DATA_WIDTH = 8;

  logic i_PCLK = 0;                 
  logic i_PWRITE;
  logic i_PENABLE;                  
  logic i_PRESETn;                  
  logic [ADDR_WIDTH-1:0] i_PADDR;   
  logic [DATA_WIDTH-1:0] i_PWDATA;
  logic [SEL_WIDTH-1:0] i_PSEL;    

  logic o_PREADY;
  logic [DATA_WIDTH-1:0] o_PRDATA;
  logic [3:0] o_PSLVERR;

  always #1 i_PCLK = ~i_PCLK;

  apb_exe_unit_2 #(.SEL_WIDTH(SEL_WIDTH), .ADDR_WIDTH(ADDR_WIDTH), .DATA_WIDTH(DATA_WIDTH), .SEL_BIT(2)) slave (
  .i_PCLK(i_PCLK), 
  .i_PWRITE(i_PWRITE), 
  .i_PENABLE(i_PENABLE), 
  .i_PRESETn(i_PRESETn),
  .i_PADDR(i_PADDR), 
  .i_PWDATA(i_PWDATA), 
  .i_PSEL(i_PSEL),

  .o_PREADY(o_PREADY),
  .o_PRDATA(o_PRDATA),
  .o_PSLVERR(o_PSLVERR)
  );

   initial begin

    $dumpfile("./TEST/VCD/tb_apb_exe_unit_2.vcd");
    $dumpvars(0, testbench);

    // Inicjalizacja

    i_PWRITE = 1;
    i_PRESETn = 0;
    i_PENABLE = 'b0;

    i_PADDR = 'b0;
    i_PWDATA = 'b0;
    i_PSEL = 'b0;

    #6;
    i_PRESETn = 0;
    i_PENABLE = 'b0;

    #6;
    i_PRESETn = 1;


    // Przesun 1010 o 1 bit w lewo z zachowaniem znaku
    #6;
    i_PWRITE = 1;
    i_PADDR = 'b01;
    i_PSEL = 3'b001;
    i_PWDATA = 'b00011010;

    #2;
    i_PENABLE = 'b1;

    #8;
    i_PENABLE = 'b0;
    i_PWDATA = 'b0;
    i_PSEL = 3'b000;
    i_PADDR = 'b00;

    // Odczyt
    #6;
    i_PWRITE = 0;
    i_PENABLE = 'b0;
    i_PWDATA = 'b0;
    i_PSEL = 3'b001;
    i_PADDR = 'b00;

    #2;
    i_PENABLE = 'b1;

    #8;
    i_PENABLE = 'b0;
    i_PWDATA = 'b0;
    i_PSEL = 3'b000;
    i_PADDR = 'b00;

    // Przekonwertuj 1010 na ZM
    #6;
    i_PWRITE = 1;
    i_PADDR = 'b00;
    i_PSEL = 3'b001;
    i_PWDATA = 'b00101010;

    #2;
    i_PENABLE = 'b1;

    #8;
    i_PENABLE = 'b0;
    i_PWDATA = 'b0;
    i_PSEL = 3'b000;
    i_PADDR = 'b00;

    // Odczyt
    #6;
    i_PWRITE = 0;
    i_PENABLE = 'b0;
    i_PWDATA = 'b0;
    i_PSEL = 3'b001;
    i_PADDR = 'b00;

    #2;
    i_PENABLE = 'b1;

    #8;
    i_PENABLE = 'b0;
    i_PWDATA = 'b0;
    i_PSEL = 3'b000;
    i_PADDR = 'b00;

    
    // Przesun 1010 o 1 bit w lewo z zachowaniem znaku
    #6;
    i_PWRITE = 1;
    i_PADDR = 'b11;
    i_PSEL = 3'b001;
    i_PWDATA = 'b00001010;

    #2;
    i_PENABLE = 'b1;

    #8;
    i_PENABLE = 'b0;
    i_PWDATA = 'b0;
    i_PSEL = 3'b000;
    i_PADDR = 'b00;

    // Odczyt
    #6;
    i_PWRITE = 0;
    i_PENABLE = 'b0;
    i_PWDATA = 'b0;
    i_PSEL = 3'b001;
    i_PADDR = 'b00;

    #2;
    i_PENABLE = 'b1;

    #8;
    i_PENABLE = 'b0;
    i_PWDATA = 'b0;
    i_PSEL = 3'b000;
    i_PADDR = 'b00;

    // Przesun 1010 o 1 bit w lewo z zachowaniem znaku
    #6;
    i_PWRITE = 1;
    i_PADDR = 'b10;
    i_PSEL = 3'b001;
    i_PWDATA = 'b00110010;

    #2;
    i_PENABLE = 'b1;

    #8;
    i_PENABLE = 'b0;
    i_PWDATA = 'b0;
    i_PSEL = 3'b000;
    i_PADDR = 'b00;

    // Odczyt
    #6;
    i_PWRITE = 0;
    i_PENABLE = 'b0;
    i_PWDATA = 'b0;
    i_PSEL = 3'b001;
    i_PADDR = 'b00;

    #2;
    i_PENABLE = 'b1;

    #8;
    i_PENABLE = 'b0;
    i_PWDATA = 'b0;
    i_PSEL = 3'b000;
    i_PADDR = 'b00;

  end

  initial #150 $finish;

endmodule

TEST/VCD/tb_apb_exe_unit_2.vcd
$date
	Tue Jan 23 15:31:17 2024
$end
$version
	Icarus Verilog
$end
$timescale
	1s
$end
$scope module testbench $end
$var wire 4 ! o_PSLVERR [3:0] $end
$var wire 1 " o_PREADY $end
$var wire 8 # o_PRDATA [7:0] $end
$var parameter 32 $ ADDR_WIDTH $end
$var parameter 32 % DATA_WIDTH $end
$var parameter 32 & SEL_WIDTH $end
$var reg 2 ' i_PADDR [1:0] $end
$var reg 1 ( i_PCLK $end
$var reg 1 ) i_PENABLE $end
$var reg 1 * i_PRESETn $end
$var reg 3 + i_PSEL [2:0] $end
$var reg 8 , i_PWDATA [7:0] $end
$var reg 1 - i_PWRITE $end
$scope module slave $end
$var wire 2 . i_PADDR [1:0] $end
$var wire 1 ( i_PCLK $end
$var wire 1 ) i_PENABLE $end
$var wire 1 * i_PRESETn $end
$var wire 3 / i_PSEL [2:0] $end
$var wire 8 0 i_PWDATA [7:0] $end
$var wire 1 - i_PWRITE $end
$var wire 4 1 s_result [3:0] $end
$var wire 4 2 s_pslverr [3:0] $end
$var parameter 32 3 ADDR_WIDTH $end
$var parameter 32 4 DATA_WIDTH $end
$var parameter 32 5 SEL_BIT $end
$var parameter 32 6 SEL_WIDTH $end
$var reg 8 7 o_PRDATA [7:0] $end
$var reg 1 " o_PREADY $end
$var reg 4 8 o_PSLVERR [3:0] $end
$var reg 2 9 s_PADDR [1:0] $end
$var reg 8 : s_PWDATA [7:0] $end
$scope module slave $end
$var wire 4 ; i_argA [3:0] $end
$var wire 4 < i_argB [3:0] $end
$var wire 1 ( i_clk $end
$var wire 2 = i_oper [1:0] $end
$var wire 1 > i_rsn $end
$var wire 4 ? o_result_3 [3:0] $end
$var wire 4 @ o_result_2 [3:0] $end
$var wire 4 A o_result_1 [3:0] $end
$var wire 4 B o_result_0 [3:0] $end
$var wire 1 C error_3 $end
$var wire 1 D error_2 $end
$var wire 1 E error_0 $end
$var parameter 32 F BITS $end
$var parameter 32 G N $end
$var reg 1 H error $end
$var reg 4 I o_result [3:0] $end
$var reg 4 J o_status [3:0] $end
$var reg 1 K overflow $end
$var integer 32 L i [31:0] $end
$var integer 32 M x [31:0] $end
$scope module changebit $end
$var wire 4 N i_argA [3:0] $end
$var wire 4 O i_argB [3:0] $end
$var parameter 32 P BITS $end
$var reg 1 D error $end
$var reg 4 Q o_result [3:0] $end
$upscope $end
$scope module changecode $end
$var wire 4 R i_argA [3:0] $end
$var parameter 32 S BITS $end
$var reg 1 C error $end
$var reg 4 T o_result [3:0] $end
$upscope $end
$scope module comparison $end
$var wire 4 U i_argA [3:0] $end
$var wire 4 V i_argB [3:0] $end
$var parameter 32 W BITS $end
$var reg 4 X o_result [3:0] $end
$upscope $end
$scope module negation $end
$var wire 4 Y i_argA [3:0] $end
$var parameter 32 Z BITS $end
$var reg 1 E error $end
$var reg 4 [ o_result [3:0] $end
$upscope $end
$upscope $end
$upscope $end
$upscope $end
$enddefinitions $end
$comment Show the parameter values. $end
$dumpall
b100 Z
b100 W
b100 S
b100 P
b10 G
b100 F
b11 6
b10 5
b1000 4
b10 3
b11 &
b1000 %
b10 $
$end
#0
$dumpvars
bx [
bx Y
b0 X
bx V
bx U
b1xxx T
bx R
bx Q
bx O
bx N
bx M
bx L
xK
bx J
bx I
xH
0E
0D
0C
bx B
b0 A
bx @
b1xxx ?
z>
bx =
bx <
bx ;
bx :
bx 9
b0 8
b0 7
bx 2
bx 1
b0 0
b0 /
b0 .
1-
b0 ,
b0 +
0*
0)
0(
b0 '
b0 #
0"
b0 !
$end
#1
b100 L
b0 M
b1 2
b1 J
b0 1
b0 I
1(
#2
0(
#3
b100 L
1(
#4
0(
#5
b100 L
1(
#6
0(
#7
b100 L
1(
#8
0(
#9
b100 L
1(
#10
0(
#11
b100 L
1(
#12
0(
1*
#13
b100 L
1(
#14
0(
#15
b100 L
1(
#16
0(
#17
b100 L
1(
#18
0(
b11010 ,
b11010 0
b1 +
b1 /
b1 '
b1 .
#19
b100 L
1(
#20
0(
1)
#21
b100 L
1(
#22
0(
#23
b100 L
1(
#24
0(
#25
b100 L
1(
#26
0(
#27
b100 L
1(
#28
0(
b0 '
b0 .
b0 +
b0 /
b0 ,
b0 0
0)
#29
b100 L
1(
#30
0(
#31
b100 L
1(
#32
0(
#33
b100 L
1(
#34
0(
b1 +
b1 /
0-
#35
b100 L
1(
#36
0(
1)
#37
b100 L
1(
#38
0(
#39
b100 L
1(
#40
0(
#41
b100 L
1(
#42
0(
#43
b100 L
1(
#44
0(
b0 +
b0 /
0)
#45
b100 L
1(
#46
0(
#47
b100 L
1(
#48
0(
#49
b100 L
1(
#50
0(
b101010 ,
b101010 0
b1 +
b1 /
1-
#51
b100 L
1(
#52
0(
1)
#53
b100 L
1(
#54
0(
#55
b100 L
1(
#56
0(
#57
b100 L
1(
#58
0(
#59
b100 L
1(
#60
0(
b0 +
b0 /
b0 ,
b0 0
0)
#61
b100 L
1(
#62
0(
#63
b100 L
1(
#64
0(
#65
b100 L
1(
#66
0(
b1 +
b1 /
0-
#67
b100 L
1(
#68
0(
1)
#69
b100 L
1(
#70
0(
#71
b100 L
1(
#72
0(
#73
b100 L
1(
#74
0(
#75
b100 L
1(
#76
0(
b0 +
b0 /
0)
#77
b100 L
1(
#78
0(
#79
b100 L
1(
#80
0(
#81
b100 L
1(
#82
0(
b1010 ,
b1010 0
b1 +
b1 /
b11 '
b11 .
1-
#83
b100 L
1(
#84
0(
1)
#85
b100 L
1(
#86
0(
#87
b100 L
1(
#88
0(
#89
b100 L
1(
#90
0(
#91
b100 L
1(
#92
0(
b0 '
b0 .
b0 +
b0 /
b0 ,
b0 0
0)
#93
b100 L
1(
#94
0(
#95
b100 L
1(
#96
0(
#97
b100 L
1(
#98
0(
b1 +
b1 /
0-
#99
b100 L
1(
#100
0(
1)
#101
b100 L
1(
#102
0(
#103
b100 L
1(
#104
0(
#105
b100 L
1(
#106
0(
#107
b100 L
1(
#108
0(
b0 +
b0 /
0)
#109
b100 L
1(
#110
0(
#111
b100 L
1(
#112
0(
#113
b100 L
1(
#114
0(
b110010 ,
b110010 0
b1 +
b1 /
b10 '
b10 .
1-
#115
b100 L
1(
#116
0(
1)
#117
b100 L
1(
#118
0(
#119
b100 L
1(
#120
0(
#121
b100 L
1(
#122
0(
#123
b100 L
1(
#124
0(
b0 '
b0 .
b0 +
b0 /
b0 ,
b0 0
0)
#125
b100 L
1(
#126
0(
#127
b100 L
1(
#128
0(
#129
b100 L
1(
#130
0(
b1 +
b1 /
0-
#131
b100 L
1(
#132
0(
1)
#133
b100 L
1(
#134
0(
#135
b100 L
1(
#136
0(
#137
b100 L
1(
#138
0(
#139
b100 L
1(
#140
0(
b0 +
b0 /
0)
#141
b100 L
1(
#142
0(
#143
b100 L
1(
#144
0(
#145
b100 L
1(
#146
0(
#147
b100 L
1(
#148
0(
#149
b100 L
1(
