MODEL/apb_exe_unit_1/exe_unit_1/src/modules/register.sv
module register #(parameter N=8) (
  input logic clk,      
  input logic reset,    
  input logic [N-1:0] in, 
  output logic [N-1:0] out   
);

 always_ff @(posedge clk) begin // sync reset
    if (reset == 1'b0)
      out <= '0;
    else
      out <= in;
 end

endmodule

MODEL/apb_exe_unit_1/exe_unit_1/src/modules/mux_4to1.sv
module mux_4to1 #(parameter N=8)(
  input [N-1:0] in0,        // Linie danych wejściowych N-bitowych
  input [N-1:0] in1,
  input [N-1:0] in2,
  input [N-1:0] in3,
  input [1:0] sel,          // Linie selekcji w kodzie Graya (2-bitowy)
  output logic [N-1:0] out    // Linia danych wyjściowych N-bitowa
);

  always_comb begin
    case(sel)
      2'b00: out = in0;
      2'b01: out = in1;
      2'b11: out = in2;
      2'b10: out = in3;
    endcase
  end

endmodule

MODEL/apb_exe_unit_1/exe_unit_1/src/modules/compare.sv
module compare #(parameter N=8)(
    input logic signed [N-1:0] A,         // Wejście A (Liczba o N bitach w formacie ze znakiem)
    input logic signed [N-1:0] B,         // Wejście B (Liczba o N bitach w formacie ze znakiem)
    output logic [N-1:0] result           // Wynik porównania A < B
);

always_comb begin
    if( A < B) begin
        result = 'b1;
    end else begin
        result = 'b0;
    end
end

endmodule

MODEL/apb_exe_unit_1/exe_unit_1/src/modules/bit_change.sv
module bit_change #(parameter N=8)(
    input logic [N-1:0] A,        // Wejście liczby A (N bitów)
    input logic [N-1:0] B,        // Wejście indeksu B (N bitów)
    output logic [N-1:0] result,  // Wyjście zmodyfikowane A
    output logic error            // Wyjście sygnalizujące błąd
);

always_comb begin
    if (B >= N || B < 0) begin
        error = 1;              // Ustaw flagę błędu jeżeli B jest poza zakresem
        result = A;             // Wyjście A bez zmian
    end
    else begin
        error = 0;               // Wyczyść flagę błędu jeżeli B jest w zakresie
        result = A | (1 << B);   // Ustaw B-ty bit A na 1
    end
end

endmodule

MODEL/apb_exe_unit_1/exe_unit_1/src/modules/left_shift.sv
module left_shift #(parameter N=8)(
    input logic signed [N-1:0] A,         // Wejście A (Liczba o N bitach w formacie ze znakiem)
    input logic signed [N-1:0] B,         // Wejście B (Liczba o N bitach w formacie ze znakiem)
    output logic signed [N-1:0] result,   // Wynik przesunięcia A o B bitów
    output logic error                    // Sygnał błędu jeśli B < 0
);

reg signed [N-1:0] shifted_A;

// always_comb powoduje dodatkowe błędy 
always @(*) begin
    result = 0;     
    if (B < 0) begin                    // Gdy B jest ujemne, wynik jest niezdefiniowany
        error = 1;                      // Ustaw sygnał błędu na wysoki
    end
    else begin                          
        error = 0;
        shifted_A = A <<< B;                    // Przesuń A o B w lewo
        result = {A[N-1], shifted_A[N-2:0]};    // Połącz bit znaku z A razem z fragmentem przesuniętej wartości
    end
end

endmodule

MODEL/apb_exe_unit_1/exe_unit_1/src/modules/u2_to_sm.sv
module u2_to_sm #(parameter N=8)(
    input logic [N-1:0] u2_number,    // Wejście U2 (Liczba o N bitach)
    output logic [N-1:0] sm_number,   // Wyjście Znak-Moduł
    output logic error                // Sygnał błędu
);

// always_comb powoduje dodatkowe błędy
always @(*) begin
    if (u2_number[N-1] == 1) begin
        sm_number = {1'b1, {~u2_number[N-2:0]}} + 1; // Konwersja do systemu znak-moduł
        error = sm_number[N-1] == 0;                 // Sprawdź czy wystąpiło przepełnienie
    end
    else begin                         
        sm_number = u2_number;         // Liczba dodatnia, już w reprezentacji SM
        error = 0;                     // Wyczyść flagę błędu
    end
end

endmodule

MODEL/apb_exe_unit_1/exe_unit_1/src/modules/exe_unit_w26.sv
`include "./MODEL/apb_exe_unit_1/exe_unit_1/src/modules/register.sv"
`include "./MODEL/apb_exe_unit_1/exe_unit_1/src/modules/u2_to_sm.sv"
`include "./MODEL/apb_exe_unit_1/exe_unit_1/src/modules/mux_4to1.sv"
`include "./MODEL/apb_exe_unit_1/exe_unit_1/src/modules/left_shift.sv"
`include "./MODEL/apb_exe_unit_1/exe_unit_1/src/modules/compare.sv"
`include "./MODEL/apb_exe_unit_1/exe_unit_1/src/modules/bit_change.sv"

module exe_unit_w26 #(parameter N=2, parameter M=8)(
    input logic [N-1:0] i_oper,
    input logic [M-1:0] i_argA,
    input logic [M-1:0] i_argB,
    input logic i_clk,
    input logic i_rsn,
    output logic [M-1:0] o_result,
    output logic [4-1:0] o_status
);

  logic err_conversion;
  logic err_left_shift;
  logic err_bit_change;
  logic [M-1:0] out_conversion;
  logic [M-1:0] out_shift;
  logic [M-1:0] out_bit_change;
  logic [M-1:0] out_compare;
  logic [M-1:0] out_mux;

  u2_to_sm #(M) conversion (
    .u2_number(i_argA),
    .sm_number(out_conversion),
    .error(err_conversion)
  );

  left_shift #(M) shift (
    .A(i_argA),
    .B(i_argB),
    .result(out_shift),
    .error(err_left_shift)
  );

  bit_change #(M) bit_change (
    .A(i_argA),
    .B(i_argB),
    .result(out_bit_change),
    .error(err_bit_change)
  );

  compare #(M) compare (
    .A(i_argA),
    .B(i_argB),
    .result(out_compare)
  );

  mux_4to1 #(M) mux (
    .in0(out_conversion),   //00
    .in1(out_shift),        //01
    .in2(out_bit_change),   //11
    .in3(out_compare),      //10
    .sel(i_oper),
    .out(out_mux)
  );

  register #(M) register (
    .clk(i_clk),
    .reset(i_rsn),
    .in(out_mux),
    .out(o_result)
  );


  logic [4-1:0] info;

  register #(4) status_register (
    .clk(i_clk),
    .reset(i_rsn),
    .in(info),
    .out(o_status)
  );

  integer count, i;

  always_comb begin
      count = 0;

      for( i = 0; i < M; i=i+1) 
      begin
        if(o_result[i] == 1) begin
          count = count + 1;
        end
      end

      info[0] = err_left_shift || err_bit_change;   // Błędy ogólne
      info[1] = (count%2 == 0);                     // Parzysta liczba jedynek
      info[2] = (o_result == {M{1'b1}});            // Same jedynki
      info[3] = err_conversion;                     // Błąd przepełnienia
  end

endmodule

MODEL/apb_exe_unit_1/apb_exe_unit_1.sv
`include "./MODEL/apb_exe_unit_1/exe_unit_1/src/modules/exe_unit_w26.sv"

// iverilog -g2005-sv -o ./TEST/VVP/apb_exe_unit_1.vvp ./MODEL/apb_exe_unit_1/apb_exe_unit_1.sv

module apb_exe_unit_1 #(
    parameter SEL_WIDTH = 3,
    parameter ADDR_WIDTH = 2,
    parameter DATA_WIDTH = 32,
    parameter SEL_BIT = 1
)(
    input logic i_PCLK,                     
    input logic i_PWRITE,
    input logic i_PENABLE,                  
    input logic i_PRESETn,  
    input logic [ADDR_WIDTH-1:0] i_PADDR,   
    input logic [DATA_WIDTH-1:0] i_PWDATA,     
    input logic [SEL_WIDTH-1:0] i_PSEL,
       
    output logic o_PREADY,
    output logic o_PSLVERR,
    output logic [DATA_WIDTH-1:0] o_PRDATA
);

    logic s_pslverr;

    logic [DATA_WIDTH/2-1:0] s_result;
    logic [ADDR_WIDTH-1:0] s_PADDR;   
    logic [DATA_WIDTH-1:0] s_PWDATA;     


    exe_unit_w26 #(.N(ADDR_WIDTH), .M(DATA_WIDTH/2)) slave (.i_clk(i_PCLK), .i_oper(s_PADDR), .i_argA(s_PWDATA[DATA_WIDTH/2-1:0]), .i_argB(s_PWDATA[DATA_WIDTH-1:DATA_WIDTH/2]), .o_result(s_result));

    always_ff @(posedge i_PCLK or negedge i_PRESETn) begin
        s_pslverr <= 0;
        if (!i_PRESETn) begin // RESET
            o_PREADY <= 1'b0;
            o_PRDATA <= 'b0;
            o_PSLVERR <= 1'b0;
        end else if (i_PENABLE && i_PSEL[SEL_BIT-1] == 1 && i_PWRITE == 1) begin // ZAPIS (MASTER -> SLAVE)
            s_PADDR <= i_PADDR;
            s_PWDATA <= i_PWDATA;
            o_PREADY <= 1'b1;
            o_PSLVERR <= s_pslverr;
        end else if (i_PENABLE && i_PSEL[SEL_BIT-1] == 1 && i_PWRITE == 0) begin // ODCZYT (SLAVE -> MASTER)
            o_PREADY <= 1'b1;
            o_PRDATA <= {{(DATA_WIDTH/2){1'b0}},{s_result}};
            o_PSLVERR <= s_pslverr;
        end else begin
            o_PREADY <= 'b0;
            o_PRDATA <= 'b0;
            o_PSLVERR <= 'b0;
        end
    end
endmodule

MODEL/Memory_model.v
`timescale 1ns / 1ps

module Memory_model #(
   parameter   ADDR_WIDTH        = 16,             // memory address size – memory depth = 2^ADDR_WIDTH
   parameter   DATA_WIDTH        = 14,             // memory data width
   parameter   MEMORY_FILE       = "mem.data",     // file containing dump of instruction and data memory
   parameter   MEMORY_DUMP_FILE  = "mem_dump.data" // file containing dump of instruction and data memory
)(
   input  wire                   i_clk,            // clock signal
   input  wire                   i_en,             // enable
   input  wire                   i_wr,             // '1' - write, '0' - read

   input  wire[ADDR_WIDTH-1:0]   i_addr,           // address bus
   input  wire[DATA_WIDTH-1:0]   i_data_w,         // write data bus
   output reg [DATA_WIDTH-1:0]   o_data_r,         // read data bus
   
   input  wire                   i_dump,            // '1' to dump memory contents to MEMORY_DUMP_FILE

   input  wire[ADDR_WIDTH-1:0]   i_write_addr     // address bus
);

reg [DATA_WIDTH-1:0] memory [0:(1<<ADDR_WIDTH)-1];
reg [DATA_WIDTH-1:0] memory_write [0:(1<<ADDR_WIDTH)-1];

initial begin
   $readmemb(MEMORY_FILE, memory); // binary
end

always @(posedge i_clk) begin
   if (i_en) 
   begin
      if (!i_wr)
         o_data_r         <= memory[i_addr];
      else
         memory_write[i_write_addr]   <= i_data_w;
   end 
   if (i_dump)
      $writememb(MEMORY_DUMP_FILE, memory_write); // binary
end 

endmodule

MODEL/APB_master.v
`timescale 1ns / 1ps

module APB_master #(
   parameter   SEL_WIDTH                  = 1,           // PSEL width - one bit for each slave
   parameter   ADDR_WIDTH                 = 32,          // address width
   parameter   DATA_WIDTH                 = 32           // data width
)(
   // AMBA 3 APB interface
   input  wire                            i_PCLK,
   input  wire                            i_PRESETn,
   output reg [ADDR_WIDTH-1:0]            o_PADDR,
   output reg [SEL_WIDTH-1:0]             o_PSEL,
   output reg                             o_PENABLE,
   output reg                             o_PWRITE,
   output reg [DATA_WIDTH-1:0]            o_PWDATA,
   input  wire                            i_PREADY,
   input  wire[DATA_WIDTH-1:0]            i_PRDATA,
   input  wire                            i_PSLVERR,

   // User interface
   input  wire                            i_enable,      // enable transaction
   input  wire                            i_wr,          // '1' - write, '0' - read
   input  wire[$clog2(SEL_WIDTH+1)-1:0]   i_slave_idx,   // index of a selected slave
   input  wire[ADDR_WIDTH-1:0]            i_addr,        // address
   input  wire[DATA_WIDTH-1:0]            i_data_w,      // data to write
   output reg [DATA_WIDTH-1:0]            o_data_r,      // read data
   output reg                             o_data_valid,  // read data valid
   output reg                             o_busy         // module busy flag
);

reg [1:0] state;

localparam [1:0] IDLE_STATE      = 2'h0;
localparam [1:0] SETUP_STATE     = 2'h1;
localparam [1:0] ACCESS_STATE    = 2'h2;

always @(posedge i_PCLK or negedge i_PRESETn) begin
   if (!i_PRESETn) begin
      o_PADDR                    <= 'h0;
      o_PSEL                     <= 'h0;
      o_PENABLE                  <= 1'b0;
      o_PWRITE                   <= 1'b0;
      o_PWDATA                   <= 'h0;
      o_data_r                   <= 'h0;
      o_data_valid               <= 1'b0;
      o_busy                     <= 1'b0;
      state                      <= IDLE_STATE;
   end
   else begin
      case (state)
         IDLE_STATE: begin
            o_PSEL               <= 'h0;
            o_PENABLE            <= 1'b0;
            o_data_valid         <= 1'b0;
            o_busy               <= 1'b0;
            if (i_enable) begin
               o_busy            <= 1'b1;
               state             <= SETUP_STATE;
            end
         end
         SETUP_STATE: begin
            o_PSEL               <= 'h0;
            o_PSEL[i_slave_idx]  <= 1'b1;
            o_PENABLE            <= 1'b0;
            o_PADDR              <= i_addr;
            o_PWRITE             <= i_wr;
            o_data_valid         <= 1'b0;
            if (i_wr)
               o_PWDATA          <= i_data_w;
            state                <= ACCESS_STATE;
         end
         ACCESS_STATE: begin
            o_PENABLE            <= 1'b1;
            if (i_PREADY) begin
               if (!i_wr & !i_PSLVERR) begin
                  o_data_r       <= i_PRDATA;
                  o_data_valid   <= 1'b1;
               end
               if (i_enable)
                  state          <= SETUP_STATE;
               else
                  state          <= IDLE_STATE;
            end
         end
         default:
            state                <= IDLE_STATE;
      endcase
   end
end

always @(*) begin
   if ((state == ACCESS_STATE) & i_PREADY & i_PSLVERR)
      $display("Warning! Detected PSLVERR high!");
end

endmodule

MODEL/APB_controller.sv
`include "./MODEL/APB_master.v"
`include "./MODEL/Memory_model.v"

// iverilog -g2005-sv -o ./TEST/VVP/APB_controller.vvp ./MODEL/APB_controller.sv

module controller #(
    parameter SEL_WIDTH = 3,
    parameter ADDR_WIDTH = 2,
    parameter DATA_WIDTH = 16,
    parameter MEMORY_WIDTH = 14
)(
    input   logic                   CLK,
    output  logic                   o_PRESETn,   /// reset OUTPUT
    output  logic [ADDR_WIDTH-1:0]  o_PADDR,
    output  logic [SEL_WIDTH-1:0]   o_PSEL,
    output  logic                   o_PENABLE,
    output  logic                   o_PWRITE,
    output  logic [DATA_WIDTH-1:0]  o_PWDATA,
    input   logic                   i_PREADY,
    input   logic [DATA_WIDTH-1:0]  i_PRDATA,
    input   logic                   i_PSLVERR
);

    localparam [2:0] READ_STATE      = 3'h0;
    localparam [2:0] PUSH_STATE      = 3'h1;
    localparam [2:0] SAVE_STATE      = 3'h2;
    localparam [2:0] WAIT_STATE      = 3'h3;
    localparam [2:0] ANSW_STATE      = 3'h4;
    localparam [2:0] END_STATE       = 3'h5;
    localparam [2:0] DUMP_STATE      = 3'h6;
    localparam [2:0] HOLD_STATE      = 3'h7;

    reg [2:0] state = READ_STATE;

    logic busy;
    logic i_PRESETn;   /// reset OUTPUT

    APB_master #(SEL_WIDTH, ADDR_WIDTH, DATA_WIDTH) master (
    // AMBA 3 ABP interface
    .i_PCLK(CLK),
    .i_PRESETn(i_PRESETn),
    .o_PADDR(o_PADDR),
    .o_PSEL(o_PSEL),
    .o_PENABLE(o_PENABLE),
    .o_PWRITE(o_PWRITE),
    .o_PWDATA(o_PWDATA),
    .i_PREADY(i_PREADY),
    .i_PRDATA(i_PRDATA),
    .i_PSLVERR(i_PSLVERR),
    // User interface
    .i_enable(P_enable),
    .i_wr(P_wr),
    .i_slave_idx(P_slave_idx),
    .i_addr(P_addr),
    .i_data_w(P_data_w),
    .o_data_r(P_data_r),
    .o_data_valid(P_data_valid),
    .o_busy(busy)
    );

    logic P_enable;
    logic P_wr;
    logic [2-1:0]          P_slave_idx;
    logic [ADDR_WIDTH-1:0] P_addr;
    logic [DATA_WIDTH-1:0] P_data_w;
    logic [DATA_WIDTH-1:0] P_data_r;
    logic P_data_valid;

    Memory_model #(.ADDR_WIDTH(ADDR_WIDTH), .DATA_WIDTH(MEMORY_WIDTH)) memory (
        .i_clk(CLK),
        .i_en(i_en),
        .i_wr(i_wr),
        .i_addr(mem_addr),
        .i_data_w(i_data_w),
        .o_data_r(o_data_r),
        .i_dump(i_dump),
        .i_write_addr(write_addr)
    );

    logic [ADDR_WIDTH-1:0] mem_addr = 0; 
    logic [ADDR_WIDTH-1:0] write_addr = 0;
    logic [MEMORY_WIDTH-1:0] o_data_r;
    logic [MEMORY_WIDTH-1:0] i_data_w;

    logic next = 1'b1;
    logic i_en = 1;
    logic i_wr = 0;
    logic i_dump = 0;

    logic s_save = 0;
    logic s_reset = 1;

    always @(posedge CLK) begin

    case (state)
        READ_STATE: begin
            i_wr <= 0;
            i_en <= 1;
            i_dump <= 0;
            state <= PUSH_STATE;
        end

        PUSH_STATE: begin
            i_en <= 0;
            i_wr <= 0;

            {P_slave_idx, P_addr, P_data_w, s_save, s_reset, P_wr} <= {o_data_r, 1'b1};

            o_PRESETn <= s_reset;
            i_PRESETn <= s_reset;


            if (o_data_r == 0) begin
                state <= HOLD_STATE;
            end else begin
                P_enable <= 'b1;
                state <= WAIT_STATE;
            end
        end

        WAIT_STATE: begin
            if(i_PREADY) begin
                {P_slave_idx, P_addr, P_data_w, P_wr} <= 'b0;
                o_PRESETn <= 'b0;
                i_PRESETn <= 'b0;
                P_enable = 'b0;
                if(s_save) begin
                    state <= ANSW_STATE;
                end else begin
                    state <= END_STATE;
                end
            end
        end

        ANSW_STATE: begin
                P_wr <= 1'b0;
                o_PRESETn <= s_reset;
                i_PRESETn <= s_reset;
                P_enable <= 'b1;
                state <= SAVE_STATE;
        end

        SAVE_STATE: begin
            if(i_PREADY) begin
                {P_slave_idx, P_addr, P_data_w, P_wr} <= 'b0;
                o_PRESETn <= 'b0;
                i_PRESETn <= 'b0;
                P_enable <= 'b0;

                i_wr <= 1;

                i_data_w <= i_PRDATA;
                
                i_en <= 1;

                state <= END_STATE;

            end
        end

        END_STATE: begin
            mem_addr <= mem_addr + 1;
            write_addr <= write_addr + 1;
            state = READ_STATE;

            // i_wr <= 0;
            // i_en <= 0;
            // i_dump <= 1;
        end

        HOLD_STATE: begin
            i_wr <= 0;
            i_en <= 0;
            i_dump = 1;
        end
    endcase

    
    end

endmodule

TEST/tb_apb_controller.sv
`include "./MODEL/APB_controller.sv"
`include "./MODEL/apb_exe_unit_1/apb_exe_unit_1.sv"

// Komendy z poziomu sck-grupowy
// iverilog -g2005-sv -o ./TEST/VVP/tb_apb_controller.vvp ./TEST/tb_apb_controller.sv
// vvp ./TEST/VVP/tb_apb_controller.vvp   

module testbench;

  parameter SEL_WIDTH = 3;
  parameter ADDR_WIDTH = 2;
  parameter DATA_WIDTH = 8;
  parameter MEMORY_WIDTH = 14;

  logic i_PCLK = 0;

  logic i_PRESETn;
  logic [ADDR_WIDTH-1:0]  i_PADDR;
  logic [SEL_WIDTH-1:0]   i_PSEL;
  logic i_PENABLE;
  logic i_PWRITE;
  logic [DATA_WIDTH-1:0]  i_PWDATA;
  logic o_PREADY;
  logic [DATA_WIDTH-1:0]  o_PRDATA;
  logic o_PSLVERR;


    controller #( .SEL_WIDTH(SEL_WIDTH), 
    .ADDR_WIDTH(ADDR_WIDTH), 
    .DATA_WIDTH(DATA_WIDTH),
    .MEMORY_WIDTH(MEMORY_WIDTH)) cnt (
    .CLK(i_PCLK),
    .o_PRESETn(i_PRESETn),
    .o_PADDR(i_PADDR),
    .o_PSEL(i_PSEL),
    .o_PENABLE(i_PENABLE),
    .o_PWRITE(i_PWRITE),
    .o_PWDATA(i_PWDATA),
    .i_PREADY(o_PREADY),
    .i_PRDATA(o_PRDATA),
    .i_PSLVERR(o_PSLVERR)
    );

      apb_exe_unit_1 #(.SEL_WIDTH(SEL_WIDTH), .ADDR_WIDTH(ADDR_WIDTH), .DATA_WIDTH(DATA_WIDTH), .SEL_BIT(1)) slave (
    .i_PCLK(i_PCLK), 
    .i_PWRITE(i_PWRITE), 
    .i_PENABLE(i_PENABLE), 
    .i_PRESETn(i_PRESETn),
    .i_PADDR(i_PADDR), 
    .i_PWDATA(i_PWDATA), 
    .i_PSEL(i_PSEL),

    .o_PREADY(o_PREADY),
    .o_PRDATA(o_PRDATA),
    .o_PSLVERR(o_PSLVERR)
    );



  always #1 i_PCLK = ~i_PCLK;


   initial begin

    $dumpfile("./TEST/VCD/tb_apb_controller.vcd");
    $dumpvars(0, testbench);


  end

  initial #150 $finish;

endmodule

TEST/VCD/tb_apb_controller.vcd
$date
	Wed Jan 24 01:54:13 2024
$end
$version
	Icarus Verilog
$end
$timescale
	1ps
$end
$scope module testbench $end
$var wire 1 ! o_PSLVERR $end
$var wire 1 " o_PREADY $end
$var wire 8 # o_PRDATA [7:0] $end
$var wire 1 $ i_PWRITE $end
$var wire 8 % i_PWDATA [7:0] $end
$var wire 3 & i_PSEL [2:0] $end
$var wire 1 ' i_PRESETn $end
$var wire 1 ( i_PENABLE $end
$var wire 2 ) i_PADDR [1:0] $end
$var parameter 32 * ADDR_WIDTH $end
$var parameter 32 + DATA_WIDTH $end
$var parameter 32 , MEMORY_WIDTH $end
$var parameter 32 - SEL_WIDTH $end
$var reg 1 . i_PCLK $end
$scope module cnt $end
$var wire 1 . CLK $end
$var wire 14 / o_data_r [13:0] $end
$var wire 1 $ o_PWRITE $end
$var wire 8 0 o_PWDATA [7:0] $end
$var wire 3 1 o_PSEL [2:0] $end
$var wire 1 ( o_PENABLE $end
$var wire 2 2 o_PADDR [1:0] $end
$var wire 1 ! i_PSLVERR $end
$var wire 1 " i_PREADY $end
$var wire 8 3 i_PRDATA [7:0] $end
$var wire 1 4 busy $end
$var wire 1 5 P_data_valid $end
$var wire 8 6 P_data_r [7:0] $end
$var parameter 32 7 ADDR_WIDTH $end
$var parameter 3 8 ANSW_STATE $end
$var parameter 32 9 DATA_WIDTH $end
$var parameter 3 : DUMP_STATE $end
$var parameter 3 ; END_STATE $end
$var parameter 3 < HOLD_STATE $end
$var parameter 32 = MEMORY_WIDTH $end
$var parameter 3 > PUSH_STATE $end
$var parameter 3 ? READ_STATE $end
$var parameter 3 @ SAVE_STATE $end
$var parameter 32 A SEL_WIDTH $end
$var parameter 3 B WAIT_STATE $end
$var reg 2 C P_addr [1:0] $end
$var reg 8 D P_data_w [7:0] $end
$var reg 1 E P_enable $end
$var reg 2 F P_slave_idx [1:0] $end
$var reg 1 G P_wr $end
$var reg 1 H i_PRESETn $end
$var reg 14 I i_data_w [13:0] $end
$var reg 1 J i_dump $end
$var reg 1 K i_en $end
$var reg 1 L i_wr $end
$var reg 2 M mem_addr [1:0] $end
$var reg 1 N next $end
$var reg 1 ' o_PRESETn $end
$var reg 1 O s_reset $end
$var reg 1 P s_save $end
$var reg 3 Q state [2:0] $end
$var reg 2 R write_addr [1:0] $end
$scope module master $end
$var wire 1 . i_PCLK $end
$var wire 1 H i_PRESETn $end
$var wire 2 S i_addr [1:0] $end
$var wire 8 T i_data_w [7:0] $end
$var wire 1 E i_enable $end
$var wire 2 U i_slave_idx [1:0] $end
$var wire 1 G i_wr $end
$var wire 1 ! i_PSLVERR $end
$var wire 1 " i_PREADY $end
$var wire 8 V i_PRDATA [7:0] $end
$var parameter 2 W ACCESS_STATE $end
$var parameter 32 X ADDR_WIDTH $end
$var parameter 32 Y DATA_WIDTH $end
$var parameter 2 Z IDLE_STATE $end
$var parameter 32 [ SEL_WIDTH $end
$var parameter 2 \ SETUP_STATE $end
$var reg 2 ] o_PADDR [1:0] $end
$var reg 1 ( o_PENABLE $end
$var reg 3 ^ o_PSEL [2:0] $end
$var reg 8 _ o_PWDATA [7:0] $end
$var reg 1 $ o_PWRITE $end
$var reg 1 4 o_busy $end
$var reg 8 ` o_data_r [7:0] $end
$var reg 1 5 o_data_valid $end
$var reg 2 a state [1:0] $end
$upscope $end
$scope module memory $end
$var wire 2 b i_addr [1:0] $end
$var wire 1 . i_clk $end
$var wire 14 c i_data_w [13:0] $end
$var wire 1 J i_dump $end
$var wire 1 K i_en $end
$var wire 1 L i_wr $end
$var wire 2 d i_write_addr [1:0] $end
$var parameter 32 e ADDR_WIDTH $end
$var parameter 32 f DATA_WIDTH $end
$var parameter 104 g MEMORY_DUMP_FILE $end
$var parameter 64 h MEMORY_FILE $end
$var reg 14 i o_data_r [13:0] $end
$upscope $end
$upscope $end
$scope module slave $end
$var wire 2 j i_PADDR [1:0] $end
$var wire 1 . i_PCLK $end
$var wire 1 ( i_PENABLE $end
$var wire 1 ' i_PRESETn $end
$var wire 3 k i_PSEL [2:0] $end
$var wire 8 l i_PWDATA [7:0] $end
$var wire 1 $ i_PWRITE $end
$var wire 4 m s_result [3:0] $end
$var parameter 32 n ADDR_WIDTH $end
$var parameter 32 o DATA_WIDTH $end
$var parameter 32 p SEL_BIT $end
$var parameter 32 q SEL_WIDTH $end
$var reg 8 r o_PRDATA [7:0] $end
$var reg 1 " o_PREADY $end
$var reg 1 ! o_PSLVERR $end
$var reg 2 s s_PADDR [1:0] $end
$var reg 8 t s_PWDATA [7:0] $end
$var reg 1 u s_pslverr $end
$scope module slave $end
$var wire 4 v i_argA [3:0] $end
$var wire 4 w i_argB [3:0] $end
$var wire 1 . i_clk $end
$var wire 2 x i_oper [1:0] $end
$var wire 1 y i_rsn $end
$var wire 4 z out_shift [3:0] $end
$var wire 4 { out_mux [3:0] $end
$var wire 4 | out_conversion [3:0] $end
$var wire 4 } out_compare [3:0] $end
$var wire 4 ~ out_bit_change [3:0] $end
$var wire 4 !" o_status [3:0] $end
$var wire 4 "" o_result [3:0] $end
$var wire 1 #" err_left_shift $end
$var wire 1 $" err_conversion $end
$var wire 1 %" err_bit_change $end
$var parameter 32 &" M $end
$var parameter 32 '" N $end
$var reg 4 (" info [3:0] $end
$var integer 32 )" count [31:0] $end
$var integer 32 *" i [31:0] $end
$scope module bit_change $end
$var wire 4 +" A [3:0] $end
$var wire 4 ," B [3:0] $end
$var parameter 32 -" N $end
$var reg 1 %" error $end
$var reg 4 ." result [3:0] $end
$upscope $end
$scope module compare $end
$var wire 4 /" A [3:0] $end
$var wire 4 0" B [3:0] $end
$var parameter 32 1" N $end
$var reg 4 2" result [3:0] $end
$upscope $end
$scope module conversion $end
$var wire 4 3" u2_number [3:0] $end
$var parameter 32 4" N $end
$var reg 1 $" error $end
$var reg 4 5" sm_number [3:0] $end
$upscope $end
$scope module mux $end
$var wire 4 6" in0 [3:0] $end
$var wire 4 7" in2 [3:0] $end
$var wire 4 8" in3 [3:0] $end
$var wire 2 9" sel [1:0] $end
$var wire 4 :" in1 [3:0] $end
$var parameter 32 ;" N $end
$var reg 4 <" out [3:0] $end
$upscope $end
$scope module register $end
$var wire 1 . clk $end
$var wire 4 =" in [3:0] $end
$var wire 1 y reset $end
$var parameter 32 >" N $end
$var reg 4 ?" out [3:0] $end
$upscope $end
$scope module shift $end
$var wire 4 @" A [3:0] $end
$var wire 4 A" B [3:0] $end
$var parameter 32 B" N $end
$var reg 1 #" error $end
$var reg 4 C" result [3:0] $end
$var reg 4 D" shifted_A [3:0] $end
$upscope $end
$scope module status_register $end
$var wire 1 . clk $end
$var wire 4 E" in [3:0] $end
$var wire 1 y reset $end
$var parameter 32 F" N $end
$var reg 4 G" out [3:0] $end
$upscope $end
$upscope $end
$upscope $end
$upscope $end
$enddefinitions $end
$comment Show the parameter values. $end
$dumpall
b100 F"
b100 B"
b100 >"
b100 ;"
b100 4"
b100 1"
b100 -"
b10 '"
b100 &"
b11 q
b1 p
b1000 o
b10 n
b110110101100101011011010010111001100100011000010111010001100001 h
b1101101011001010110110101011111011001000111010101101101011100000010111001100100011000010111010001100001 g
b1110 f
b10 e
b1 \
b11 [
b0 Z
b1000 Y
b10 X
b10 W
b11 B
b11 A
b10 @
b0 ?
b1 >
b1110 =
b111 <
b101 ;
b110 :
b1000 9
b100 8
b10 7
b11 -
b1110 ,
b1000 +
b10 *
$end
#0
$dumpvars
bx G"
bx1x E"
bx D"
bx C"
bx A"
bx @"
bx ?"
bx ="
bx <"
bx :"
bx 9"
b0 8"
bx 7"
bx 6"
bx 5"
bx 3"
b0 2"
bx 0"
bx /"
bx ."
bx ,"
bx +"
b100 *"
b0 )"
bx1x ("
0%"
x$"
x#"
bx ""
bx !"
bx ~
b0 }
bx |
bx {
bx z
zy
bx x
bx w
bx v
xu
bx t
bx s
bx r
bx m
bx l
bx k
bx j
bx i
b0 d
bx c
b0 b
bx a
bx `
bx _
bx ^
bx ]
bx V
bx U
bx T
bx S
b0 R
b0 Q
0P
1O
1N
b0 M
0L
1K
0J
bx I
xH
xG
bx F
xE
bx D
bx C
bx 6
x5
x4
bx 3
bx 2
bx 1
bx 0
bx /
0.
bx )
x(
x'
bx &
bx %
x$
bx #
x"
x!
$end
#1000
b0 a
b1101011 /
b1101011 i
b1 Q
bx1x !"
bx1x G"
0!
b0 #
b0 3
b0 V
b0 r
0"
0u
1.
#2000
0.
#3000
04
05
0(
b0 &
b0 1
b0 ^
b0 k
b11 Q
1E
1H
1'
b0 F
b0 U
b0 C
b0 S
b11010 D
b11010 T
1P
1G
0K
1.
#4000
0.
#5000
b1 a
14
1.
#6000
0.
#7000
b10 a
b11010 %
b11010 0
b11010 _
b11010 l
1$
b0 )
b0 2
b0 ]
b0 j
b1 &
b1 1
b1 ^
b1 k
1.
#8000
0.
#9000
1(
1.
#10000
0.
#11000
b0x10 ("
b0x10 E"
b100 *"
b1110 {
b1110 <"
b1110 ="
0$"
b1110 |
b1110 5"
b1110 6"
b1010 ~
b1010 ."
b1010 7"
b1 }
b1 2"
b1 8"
b100 D"
0#"
b1100 z
b1100 :"
b1100 C"
b1010 v
b1010 +"
b1010 /"
b1010 3"
b1010 @"
b1 w
b1 ,"
b1 0"
b1 A"
1"
b11010 t
b0 s
b0 x
b0 9"
1.
#12000
0.
#13000
04
b0 6
b0 `
b0 %
b0 0
b0 _
b0 l
0$
0(
b0 &
b0 1
b0 ^
b0 k
0"
b0 ("
b0 E"
b11 )"
b100 *"
b0 a
b100 Q
0H
0'
b0 D
b0 T
0G
b1110 m
b1110 ""
b1110 ?"
b0x10 !"
b0x10 G"
0E
1.
#14000
0.
#15000
b0 !"
b0 G"
b10 Q
1E
1H
1'
1.
#16000
0.
#17000
b1 a
14
1.
#18000
0.
#19000
b10 a
b1 &
b1 1
b1 ^
b1 k
1.
#20000
0.
#21000
1(
1.
#22000
0.
#23000
b1110 #
b1110 3
b1110 V
b1110 r
1"
1.
#24000
0.
#25000
04
0(
b0 &
b0 1
b0 ^
b0 k
b0 #
b0 3
b0 V
b0 r
0"
b0 a
05
b0 6
b0 `
b101 Q
1K
b1110 I
b1110 c
1L
0E
0H
0'
1.
#26000
0.
#27000
1J
0K
0L
b1 R
b1 d
b1 M
b1 b
b0 Q
1.
#28000
0.
#29000
b1 Q
0J
1K
1.
#30000
0.
#31000
b11 Q
1E
1H
1'
b11010 D
b11010 T
1G
0K
b1100101111011 /
b1100101111011 i
1.
#32000
0.
#33000
b1 a
14
1.
#34000
0.
