MODEL/apb_exe_unit_3/exe_unit_3/include.sv
`ifndef ALU_DEF

`define ALU_DEF
`include "./MODEL/apb_exe_unit_3/exe_unit_3/bit_set/bit_set.sv"
`include "./MODEL/apb_exe_unit_3/exe_unit_3/bit_shift/bit_shift.sv"
`include "./MODEL/apb_exe_unit_3/exe_unit_3/comparator/comparator.sv"
`include "./MODEL/apb_exe_unit_3/exe_unit_3/u2_to_sm/u2_to_sm.sv"
`include "./MODEL/apb_exe_unit_3/exe_unit_3/MUX.sv"
`include "./MODEL/apb_exe_unit_3/exe_unit_3/reg.sv"
  
`endif

MODEL/apb_exe_unit_3/exe_unit_3/reg.sv
module regg #(parameter M=8)
(input logic i_clk,
 input logic i_reset,
 input logic [M-1:0] i_in,
 output logic [M-1:0] o_out);

always_ff @(posedge i_clk)
begin
    if(i_reset == 1'b1)
    o_out <= i_in;
    else 
    o_out <= '0;
    
end
endmodule

MODEL/apb_exe_unit_3/exe_unit_3/MUX.sv
module MUX #(parameter M = 8, parameter N = 2)
(input logic [M-1:0] SET,
input logic [M-1:0] SHIFT,
input logic [M-1:0] COMPARATOR,
input logic [M-1:0] CHANGER,
input [N-1:0] testcase,
output logic [M-1:0] modul);

always_comb
begin
    case(testcase)
    2'b00: modul = SET;
    2'b01: modul = SHIFT;
    2'b10: modul = COMPARATOR;
    2'b11: modul = CHANGER;
    endcase
end

endmodule

MODEL/apb_exe_unit_3/exe_unit_3/u2_to_sm/u2_to_sm.sv
module u2_to_sm #(parameter M=8)(u2, sm, ERROR);

input logic[M-1:0] u2; //M-bitowe wejscie
output logic[M-1:0] sm; //M-bitowe wyjscie (po zamianie z U2 na ZNAK-MODUL)
output logic ERROR; //blad

//changing function
always@(*) begin
    if(u2[M-1] == 1)
    begin
        sm = {1'b1, {~u2[M-2:0]}} + 1;
        ERROR = sm[M-1] == 0; //szukanie bledu typu OVERFLOW
    end
    else 
    begin
        sm = u2;
        ERROR = 0; //zerowanie bledu
    end
end

endmodule

MODEL/apb_exe_unit_3/exe_unit_3/comparator/comparator.sv
module comparator #(parameter M=8)(i_argA, i_argB, o_y);

input logic [M-1:0] i_argA; //M-bitowe wejscie A
input logic [M-1:0] i_argB; //M-bitowe wejscie B
output logic [M-1:0] o_y; //wyjscie

always @(i_argA or i_argB)
	begin
		if(i_argA > i_argB)	
			begin
				o_y = 0;
			end
		else
			begin
				o_y = 1;
			end
			
	end

endmodule

MODEL/apb_exe_unit_3/exe_unit_3/bit_shift/bit_shift.sv
module bit_shift #(parameter M=8)( i_argA, i_argB, o_y, ERROR);

	//input
	input logic [M-1:0] i_argA; //M-bitowe wejscie A
	input logic [M-1:0] i_argB; //M-bitowe wejscie B
	//output
	output logic [M-1:0] o_y; //wyjscie
	output logic ERROR; //blad
	
	always@(*) begin
		ERROR = 0; //'zerowanie' bledu na starcie
		if(i_argB < 'b0)
		begin
			ERROR = 1; //pojawienie sie bledu
			o_y = 0; //wyjscie wynosi 0
		end
		else 
		begin
			ERROR = 0; //blad sie 'zeruje'
			o_y = i_argA <<< i_argB; //left shifting
		end
	end

endmodule

MODEL/apb_exe_unit_3/exe_unit_3/bit_set/bit_set.sv
module bit_set #(parameter M=8)(i_argA, i_argB, ERROR, o_y);
    
    //inputs & outputs
    input logic [M-1:0] i_argA; //M-bitowe wejscie A
    input logic [M-1:0] i_argB; //M-bitowe wejscie B
    output logic ERROR; // wyjscie bledu
    output logic [M-1:0] o_y; //wejscie zmienionego A

    //function
        always@(*) begin
            if(i_argB < 0 || i_argB >= M)
            begin
                ERROR = 1; //Blad jezeli B jest poza zakresem
                o_y = i_argA; //Wtedy A jest bez zmian
            end
            else
            begin
                ERROR = 0; //Blad sie 'zeruje'
                o_y= i_argA;
                o_y[i_argB] = 1;
            end
        end

endmodule

MODEL/apb_exe_unit_3/exe_unit_3/exe_unit_w38.sv
`include "./MODEL/apb_exe_unit_3/exe_unit_3/include.sv"
  
module exe_unit_w38 #(parameter M=8, parameter N=2)(i_op, i_argA, i_argB, i_clk, i_reset, o_result, o_stat);
	input logic [N-1:0] i_op; //wybiera operacje - MUX
	input logic [M-1:0] i_argA; //M-bitowe wejscie A
	input logic [M-1:0] i_argB; //M-bitowe wejscie B
	input logic i_reset; //reset
	input logic i_clk; //zegar
	output logic [M-1:0] o_result; //wyjscie
	output logic [3:0] o_stat; //wyjscie dla bledow


    //sygnaly wewnetrzne
    logic [M-1:0] s_out_set; //bit_set
    logic [M-1:0] s_out_shift; //bit_shift
    logic [M-1:0] s_out_comparator; //comparator
    logic [M-1:0] s_out_changer; //u2_to_sm

    logic [M-1:0] s_oper_mux; //wyjscie z muxa, operacje
    logic s_ERROR_set; //ERROR dla bit_set
    logic s_ERROR_shift; //ERROR dla bit_shift
    logic s_ERROR_change; //ERROR dla u2_to_sm
    logic [3:0] possible_errors; //wyjscie dla wszelakich znacznikow

    //Dolaczanie modulow:
    bit_set     #(.M(M))   setter    
    (.i_argA(i_argA),
     .i_argB(i_argB),
     .o_y(s_out_set),
     .ERROR(s_ERROR_set));

    bit_shift #(.M(M)) shifter 
    (.i_argA(i_argA),
     .i_argB(i_argB),
     .o_y(s_out_shift),
     .ERROR(s_ERROR_shift));

    comparator #(.M(M)) comparator 
    (.i_argA(i_argA),
    .i_argB(i_argB),
    .o_y(s_out_comparator));

    u2_to_sm #(.M(M)) changer 
    (.u2(i_argA),
     .sm(s_out_changer),
     .ERROR(s_ERROR_change)
     );

    MUX #(.M(M), .N(N)) MUX (.SET(s_out_set),
      .SHIFT(s_out_shift),
      .COMPARATOR(s_out_comparator),
      .CHANGER(s_out_changer),
      .testcase(i_op),
      .modul(s_oper_mux)
    );

    regg #(M) register (
        .i_clk(i_clk),
        .i_reset(i_reset),
        .i_in(s_oper_mux),
        .o_out(o_result)
    );

     regg #(4) register_error (
      .i_clk(i_clk),
      .i_reset(i_reset),
      .i_in(possible_errors),
      .o_out(o_stat)
     );

    integer counter, i; //helper w zliczaniu
	always_comb
begin
    counter = 0;
    for (i = 0; i < M; i = i + 1)
    begin 
        if (o_result[i] == 1) begin
            counter = counter + 1;
        end
    end 

    possible_errors[0] = (counter % 2 == 0); // EVEN
    possible_errors[1] = (&o_result); // ONES
    possible_errors[2] = s_ERROR_change; // OVERFLOW
    possible_errors[3] = s_ERROR_set || s_ERROR_shift; // ERROR
end

    
endmodule

MODEL/apb_exe_unit_3/exe_unit_3/exe_unit_w38_tb.sv
`timescale 1ps/1ps
`include "./exe_unit_w38.sv"

module testbench;
    parameter M = 8;
    logic [1:0] i_op = 'b0;
    logic [M-1:0] i_argA;
    logic [M-1:0] i_argB;
    logic i_clk = '0;
    logic i_reset = '1;
    logic [M-1:0] result;
    logic [3:0] stat;
    
    exe_unit_w38 #(.M(M)) unit
    (.i_argA(i_argA),
     .i_argB(i_argB),
     .i_op(i_op),
     .i_reset(i_reset),
     .i_clk(i_clk),
     .o_result(result),
     .o_stat(stat));

    always #1 i_clk = ~(i_clk); //zegar

    initial begin
        $dumpfile("exe_unit_w38.vcd");
        $dumpvars(0, testbench);

    //resetowanie
        i_reset = '0;
        #2
        i_reset = '1;
        
    //testing SET
        i_op = 2'b00;
        i_clk = '0;
        i_argA = 7;
        i_argB = 8'b11000001;
        #4
        i_argA = 7;  
        i_argB = 0;
        #4 
        i_argA = 7; 
        i_argB = 11;
        #4 
        i_argA = 8'b10110000; 
        i_argB = 8'b00000000;
        #4
        i_reset = '0;
        #10
    //testing SHIFT
        i_op = 2'b01;
        i_argA = 8; 
        i_argB = 8'b10110000;
        #4
        i_argA = 8'b11000011;
        i_argB = 5;
        #4
        i_argA = 8;
        i_argB = 5;
        #4
        i_reset = '0;
        #10
    //testing COMPARATOR
        i_op = 2'b10;
        i_argA = 11;
        i_argB = 14;
        #4
        i_argA = 11;
        i_argB = 9;
        #4
        i_argA = 10;
        i_argB = 10;
        #4
        i_reset = '0;
        #10
    //testing CHANGER
        i_op = 2'b11;
        i_argA = 8'b10001001;
        #4
        i_argA = 120;
        #4
        i_argA = -128;
        #4
        i_reset = '0;
        #10    
        $finish;
    end
    initial #120 $finish;
endmodule

MODEL/apb_exe_unit_3/exe_unit_3/exe_unit_w38.vcd
$date
	Sun Dec 10 23:28:35 2023
$end
$version
	Icarus Verilog
$end
$timescale
	1ps
$end
$scope module testbench $end
$var wire 4 ! stat [3:0] $end
$var wire 8 " result [7:0] $end
$var reg 8 # i_argA [7:0] $end
$var reg 8 $ i_argB [7:0] $end
$var reg 1 % i_clk $end
$var reg 2 & i_op [1:0] $end
$var reg 1 ' i_reset $end
$scope module unit $end
$var wire 8 ( i_argA [7:0] $end
$var wire 8 ) i_argB [7:0] $end
$var wire 1 % i_clk $end
$var wire 2 * i_op [1:0] $end
$var wire 1 ' i_reset $end
$var wire 8 + s_out_shift [7:0] $end
$var wire 8 , s_out_set [7:0] $end
$var wire 8 - s_out_comparator [7:0] $end
$var wire 8 . s_out_changer [7:0] $end
$var wire 8 / s_oper_mux [7:0] $end
$var wire 1 0 s_ERROR_shift $end
$var wire 1 1 s_ERROR_set $end
$var wire 1 2 s_ERROR_change $end
$var wire 4 3 o_stat [3:0] $end
$var wire 8 4 o_result [7:0] $end
$var reg 4 5 possible_errors [3:0] $end
$var integer 32 6 counter [31:0] $end
$var integer 32 7 i [31:0] $end
$scope module MUX $end
$var wire 2 8 testcase [1:0] $end
$var wire 8 9 SHIFT [7:0] $end
$var wire 8 : SET [7:0] $end
$var wire 8 ; COMPARATOR [7:0] $end
$var wire 8 < CHANGER [7:0] $end
$var reg 8 = modul [7:0] $end
$upscope $end
$scope module changer $end
$var wire 8 > u2 [7:0] $end
$var reg 1 2 ERROR $end
$var reg 8 ? sm [7:0] $end
$upscope $end
$scope module comparator $end
$var wire 8 @ i_argA [7:0] $end
$var wire 8 A i_argB [7:0] $end
$var reg 8 B o_y [7:0] $end
$upscope $end
$scope module register $end
$var wire 1 % i_clk $end
$var wire 8 C i_in [7:0] $end
$var wire 1 ' i_reset $end
$var reg 8 D o_out [7:0] $end
$upscope $end
$scope module register_error $end
$var wire 1 % i_clk $end
$var wire 4 E i_in [3:0] $end
$var wire 1 ' i_reset $end
$var reg 4 F o_out [3:0] $end
$upscope $end
$scope module setter $end
$var wire 8 G i_argA [7:0] $end
$var wire 8 H i_argB [7:0] $end
$var reg 1 1 ERROR $end
$var reg 8 I o_y [7:0] $end
$upscope $end
$scope module shifter $end
$var wire 8 J i_argA [7:0] $end
$var wire 8 K i_argB [7:0] $end
$var reg 1 0 ERROR $end
$var reg 8 L o_y [7:0] $end
$upscope $end
$upscope $end
$upscope $end
$enddefinitions $end
#0
$dumpvars
bx L
bx K
bx J
bx I
bx H
bx G
bx F
bx1 E
bx D
bx C
bx B
bx A
bx @
bx ?
bx >
bx =
bx <
bx ;
bx :
bx 9
b0 8
b1000 7
b0 6
bx1 5
bx 4
bx 3
x2
x1
x0
bx /
bx .
bx -
bx ,
bx +
b0 *
bx )
bx (
0'
b0 &
0%
bx $
bx #
bx "
bx !
$end
#1
bx01 5
bx01 E
b1000 7
b0 "
b0 4
b0 D
b0 !
b0 3
b0 F
1%
#2
bx01 !
bx01 3
bx01 F
bx "
bx 4
bx D
b111 /
b111 =
b111 C
b10x1 5
b10x1 E
b1000 7
02
b111 .
b111 <
b111 ?
b1 -
b1 ;
b1 B
b0 +
b0 9
b0 L
00
b111 ,
b111 :
b111 I
11
b11000001 $
b11000001 )
b11000001 A
b11000001 H
b11000001 K
b111 #
b111 (
b111 >
b111 @
b111 G
b111 J
1%
1'
#3
0%
#4
b1000 5
b1000 E
b11 6
b1000 7
b111 "
b111 4
b111 D
b10x1 !
b10x1 3
b10x1 F
1%
#5
0%
#6
b1000 !
b1000 3
b1000 F
b0 5
b0 E
b1000 7
b11 6
b0 -
b0 ;
b0 B
01
b111 +
b111 9
b111 L
1%
b0 $
b0 )
b0 A
b0 H
b0 K
#7
0%
#8
b0 !
b0 3
b0 F
1%
#9
0%
#10
b1000 5
b1000 E
b1000 7
b11 6
b1 -
b1 ;
b1 B
b0 +
b0 9
b0 L
11
1%
b1011 $
b1011 )
b1011 A
b1011 H
b1011 K
#11
0%
#12
b1000 !
b1000 3
b1000 F
1%
#13
0%
#14
b0 5
b0 E
b1000 7
b11 6
b10110001 /
b10110001 =
b10110001 C
b11010000 .
b11010000 <
b11010000 ?
b0 -
b0 ;
b0 B
b10110001 ,
b10110001 :
b10110001 I
01
b10110000 +
b10110000 9
b10110000 L
1%
b0 $
b0 )
b0 A
b0 H
b0 K
b10110000 #
b10110000 (
b10110000 >
b10110000 @
b10110000 G
b10110000 J
#15
0%
#16
b1 5
b1 E
b1000 7
b100 6
b10110001 "
b10110001 4
b10110001 D
b0 !
b0 3
b0 F
1%
#17
0%
#18
b1000 7
b0 6
b0 "
b0 4
b0 D
1%
0'
#19
0%
#20
1%
#21
0%
#22
1%
#23
0%
#24
1%
#25
0%
#26
1%
#27
0%
#28
b1001 5
b1001 E
b1000 7
b1000 .
b1000 <
b1000 ?
b1 -
b1 ;
b1 B
b0 +
b0 9
b0 L
b1000 ,
b1000 :
b1000 I
11
b0 /
b0 =
b0 C
1%
b10110000 $
b10110000 )
b10110000 A
b10110000 H
b10110000 K
b1000 #
b1000 (
b1000 >
b1000 @
b1000 G
b1000 J
b1 &
b1 *
b1 8
#29
0%
#30
1%
#31
0%
#32
b1 5
b1 E
b1000 7
b1100000 /
b1100000 =
b1100000 C
b10111101 .
b10111101 <
b10111101 ?
b0 -
b0 ;
b0 B
b11100011 ,
b11100011 :
b11100011 I
01
b1100000 +
b1100000 9
b1100000 L
1%
b101 $
b101 )
b101 A
b101 H
b101 K
b11000011 #
b11000011 (
b11000011 >
b11000011 @
b11000011 G
b11000011 J
#33
0%
#34
1%
#35
0%
#36
b0 /
b0 =
b0 C
b1000 .
b1000 <
b1000 ?
b0 +
b0 9
b0 L
b101000 ,
b101000 :
b101000 I
1%
b1000 #
b1000 (
b1000 >
b1000 @
b1000 G
b1000 J
#37
0%
#38
1%
#39
0%
#40
1%
#41
0%
#42
1%
#43
0%
#44
1%
#45
0%
#46
1%
#47
0%
#48
1%
#49
0%
#50
b1 /
b1 =
b1 C
b1001 5
b1001 E
b1000 7
b1011 .
b1011 <
b1011 ?
b1 -
b1 ;
b1 B
b1011 ,
b1011 :
b1011 I
11
1%
b1110 $
b1110 )
b1110 A
b1110 H
b1110 K
b1011 #
b1011 (
b1011 >
b1011 @
b1011 G
b1011 J
b10 &
b10 *
b10 8
#51
0%
#52
1%
#53
0%
#54
b0 /
b0 =
b0 C
b0 -
b0 ;
b0 B
1%
b1001 $
b1001 )
b1001 A
b1001 H
b1001 K
#55
0%
#56
1%
#57
0%
#58
b1 /
b1 =
b1 C
b1010 .
b1010 <
b1010 ?
b1 -
b1 ;
b1 B
b1010 ,
b1010 :
b1010 I
1%
b1010 $
b1010 )
b1010 A
b1010 H
b1010 K
b1010 #
b1010 (
b1010 >
b1010 @
b1010 G
b1010 J
#59
0%
#60
1%
#61
0%
#62
1%
#63
0%
#64
1%
#65
0%
#66
1%
#67
0%
#68
1%
#69
0%
#70
1%
#71
0%
#72
b11110111 .
b11110111 <
b11110111 ?
b0 -
b0 ;
b0 B
b10001001 ,
b10001001 :
b10001001 I
b11110111 /
b11110111 =
b11110111 C
1%
b10001001 #
b10001001 (
b10001001 >
b10001001 @
b10001001 G
b10001001 J
b11 &
b11 *
b11 8
#73
0%
#74
1%
#75
0%
#76
b1111000 /
b1111000 =
b1111000 C
b1111000 .
b1111000 <
b1111000 ?
b1111000 ,
b1111000 :
b1111000 I
1%
b1111000 #
b1111000 (
b1111000 >
b1111000 @
b1111000 G
b1111000 J
#77
0%
#78
1%
#79
0%
#80
b1101 5
b1101 E
b1000 7
b0 /
b0 =
b0 C
12
b0 .
b0 <
b0 ?
b10000000 ,
b10000000 :
b10000000 I
1%
b10000000 #
b10000000 (
b10000000 >
b10000000 @
b10000000 G
b10000000 J
