MODEL/apb_exe_unit_1/exe_unit_1/src/modules/register.sv
module register #(parameter N=8) (
  input logic clk,      
  input logic reset,    
  input logic [N-1:0] in, 
  output logic [N-1:0] out   
);

 always_ff @(posedge clk) begin // sync reset
    if (reset == 1'b0)
      out <= '0;
    else
      out <= in;
 end

endmodule

MODEL/apb_exe_unit_1/exe_unit_1/src/testbench/tb_register.sv
//`include "./modules/register.sv"
`include "%INCLUDE%"

module testbench;

  parameter N = 8;

  logic clk = 0; 
  logic reset = 0;
  logic [N-1:0] in_data;
  logic [N-1:0] out_data;

  register #(N) u_register (
    .clk(clk),
    .reset(reset),
    .in(in_data),
    .out(out_data)
  );

  // Generacja sygnału zegarowego
  always #5 clk = ~clk;

  initial begin

    $dumpfile("./testbench/sim/tb_register.vcd");
    $dumpvars(0, testbench);

    $display("Test modułu register (podgląd w GTKwave)\n"); 

    reset = 1;
    in_data = 'b10101010;

    #12 reset = 0;

    #10;

    reset = 1;

    #15;

    in_data = 'b11000101;

    
  end

  initial #100 $finish;

endmodule

MODEL/apb_exe_unit_1/exe_unit_1/src/testbench/sim/tb_register.vcd
$date
	Fri Dec  1 11:31:57 2023
$end
$version
	Icarus Verilog
$end
$timescale
	1s
$end
$scope module testbench $end
$var wire 8 ! out_data [7:0] $end
$var reg 1 " clk $end
$var reg 8 # in_data [7:0] $end
$var reg 1 $ reset $end
$scope module u_register $end
$var wire 1 " clk $end
$var wire 8 % in [7:0] $end
$var wire 1 $ reset $end
$var reg 8 & out [7:0] $end
$upscope $end
$upscope $end
$enddefinitions $end
#0
$dumpvars
bx &
b10101010 %
1$
b10101010 #
0"
bx !
$end
#5
b10101010 !
b10101010 &
1"
#10
0"
#12
0$
#15
b0 !
b0 &
1"
#20
0"
#22
1$
#25
b10101010 !
b10101010 &
1"
#30
0"
#35
1"
#37
b11000101 #
b11000101 %
#40
0"
#45
b11000101 !
b11000101 &
1"
